Workbook

Sheet 0. Diccionario
A1: DICCIONARIO DE ENCABEZADOS
A2: Columna 1 = encabezado completo tal como queda en este archivo (fuente de la verdad). Columna 2 = forma abreviada (lo que va fuera del parentesis) que se usa en DP, PR, RDT, OT, 3WLA y CS -- pensada para que despues, al crear tablas de base de datos con estos formatos, no haya conflicto de nombres.
A4: Encabezado en Indicadores (completo) | B4: Encabezado abreviado (DP / PR / RDT / OT / 3WLA / CS) | C4: Observacion
A5: Item | B5: WBS | C5: En Indicadores es un correlativo pedagogico (1,2,3...); en los formatos reales siempre es el codigo WBS (##.##).
A6: Partida | B6: Partida
A7: Unid. | B7: Unid.
A8: Metrado | B8: Metrado | C8: Es el metrado contractual (linea base).
A9: Precio Unit. ($/) | B9: Precio Unit.
A10: Metrado Planificado Acumulado (a la fecha) | B10: Metrado Planificado Acumulado
A11: Metrado Ejecutado Acumulado (real) | B11: Metrado Ejecutado Acumulado
A12: Costo Real Acumulado ($/) | B12: Costo Real Acumulado
A13: Rendimiento (HH/Und) | B13: Rendimiento | C13: Al abreviar se pierde la unidad (HH/Und). Sugerido si se quiere conservarla: 'Rendimiento HH/Und' en vez de solo 'Rendimiento'.
A14: HH Reales Acumuladas | B14: HH Reales Acumuladas
A15: Monto contractual BAC ($/) | B15: Monto contractual BAC | C15: Es el mas largo de la lista. Alternativa mas corta si se prefiere maxima brevedad: 'BAC' (asi ya quedo la columna N de la hoja CS de Trazabilidad.xlsx).
A16: PV ($/) (metr.plan. x P.U.) | B16: PV
A17: EV ($/) (metr.ejec. x P.U.) | B17: EV
A18: AC ($/) (Costo Real) | B18: AC
A19: CPI (EV/AC) | B19: CPI
A20: SPI (EV/PV) | B20: SPI
A21: % Avance Fisico (EV/BAC) | B21: % Avance Fisico
A22: HH Ganadas (metr.ejec. x Rendim.) | B22: HH Ganadas
A23: IP (HH Ganadas/HH Reales acumuladas) | B23: IP

Sheet 1. Teoria EVM
A1: INDICADORES DE VALOR GANADO (EVM) + AVANCE FISICO
A2: Que mide cada indicador, con que formula, y de donde sale el dato en la practica.
A4: Indicador | B4: Que responde / mide | C4: Formula | D4: De donde sale el dato
A5: PV (Valor Planificado) | B5: Cuanto deberia llevar avanzado, a costo de presupuesto, segun la fecha de corte. | C5: PV = Metrado planificado acumulado x Precio unitario | D5: Del cronograma / lookahead: que se planifico ejecutar hasta la fecha de corte.
A6: EV (Valor Ganado) | B6: Cuanto avance real se completo, valorizado a precio de presupuesto (no a costo real). | C6: EV = Metrado ejecutado acumulado x Precio unitario | D6: Del RDT validado por Oficina Tecnica -> PR (metrado_acumulado).
A7: AC (Costo Real) | B7: Cuanto costo realmente ese avance: mano de obra, equipos, materiales y subcontratos. | C7: AC = suma de costos reales incurridos (HH+HM+materiales+subcontratos) | D7: De los registros de costo real: PR (mano de obra/equipos) + Registro de costos por servicios (materiales/subcontratos).
A8: BAC (Presupuesto Total) | B8: Presupuesto total aprobado, a costo contractual (de la partida o del proyecto). | C8: BAC = Metrado contractual x Precio unitario | D8: Del presupuesto aprobado -> DP/PR (linea base).
A9: CPI (Indice de Costo) | B9: Eficiencia del gasto: por cada sol gastado, cuanto valor se genero. >1 bien, <1 mal. | C9: CPI = EV / AC | D9: Calculado (no se registra directo, sale de EV y AC ya obtenidos).
A10: SPI (Indice de Cronograma) | B10: Eficiencia del avance EN VALOR, no en dias. >1 adelantado, <1 atrasado. | C10: SPI = EV / PV | D10: Calculado. Para dias reales de atraso hace falta el cronograma CPM (3WLA).
A11: EAC (Estimado a la Conclusion) | B11: Proyeccion de costo final si el ritmo de gasto actual (CPI) se mantiene igual. | C11: EAC = AC + (BAC - EV) / CPI | D11: Calculado sobre AC, BAC, EV y CPI ya obtenidos.
A12: VAC (Variacion a la Conclusion) | B12: Utilidad o perdida proyectada respecto al presupuesto original. | C12: VAC = BAC - EAC | D12: Calculado sobre BAC y EAC ya obtenidos.
A13: % Avance Fisico | B13: Que % del proyecto esta realmente avanzado, ponderado por el costo de cada partida. | C13: % Avance Fisico = EV / BAC | D13: Calculado. NUNCA promediar el %s de metrado de cada partida (ver nota abajo).
A15: Por que EV / BAC y no un promedio de metrados
A16: EV ya es una suma ponderada por costo: EV = Sum(cantidad_ejecutada_i x precio_unitario_i) de cada partida. Cada partida pesa segun SU PROPIO costo, no segun su cantidad cruda. Una partida de 5000 m3 de movimiento de tierras barato no debe pesar lo mismo que 18 valvulas caras solo porque tiene mas unidades. Lo mismo aplica un nivel arriba, para el Dashboard de Portafolio: Avance fisico del portafolio = Sum(EV de cada proyecto) / Sum(BAC de cada proyecto) (pesa cada proyecto por su propio presupuesto -> un proyecto de S/ 10M pesa mas que uno de S/ 100K). Como leer CPI y SPI: CPI > 1 o SPI > 1 = bien (eficiente / adelantado). CPI < 1 o SPI < 1 = mal (se gasta de mas / esta atrasado). Ambos en 1.00 = exactamente segun lo planificado.
A18: Ver hoja 2 (Datos Ficticios) y hoja 3 (Ejemplo - Calculo EVM) para un caso aplicado con formulas reales.

Sheet 2. Datos Ficticios
A1: CONSOLIDADO DE METRADOS - DATOS FICTICIOS
A2: Ejemplo pedagogico. Cambia estos numeros y observa como se mueven los indicadores en la hoja 3.
A4: Item | B4: Partida | C4: Unid. | D4: Metrado | E4: Precio Unit. ($/) | F4: Metrado Planificado Acumulado (a la fecha) | G4: Metrado Ejecutado Acumulado (real) | H4: Costo Real Acumulado ($/) | I4: Rendimiento (HH/Und) | J4: HH Reales Acumuladas
A5: 1 | B5: Movimiento de tierras | C5: m3 | D5: 5000 | E5: 25 | F5: 4000 | G5: 3800 | H5: 99500 | I5: 0.12 | J5: 480
A6: 2 | B6: Encofrado y desencofrado de zapatas | C6: m2 | D6: 800 | E6: 45 | F6: 700 | G6: 720 | H6: 30000 | I6: 0.8 | J6: 540
A7: 3 | B7: Vaciado de concreto f'c=210 kg/cm2 | C7: m3 | D7: 350 | E7: 380 | F7: 280 | G7: 260 | H7: 105000 | I7: 1.2 | J7: 350
A8: 4 | B8: Habilitacion y colocacion de acero de refuerzo | C8: kg | D8: 42000 | E8: 5.2 | F8: 36000 | G8: 37500 | H8: 190000 | I8: 0.035 | J8: 1250
A9: 5 | B9: Tendido de tuberia HDPE 200mm | C9: m | D9: 1200 | E9: 95 | F9: 900 | G9: 850 | H9: 84000 | I9: 0.25 | J9: 230
A10: 6 | B10: Instalacion y prueba de valvulas | C10: und | D10: 18 | E10: 850 | F10: 10 | G10: 12 | H10: 9600 | I10: 4 | J10: 45
A12: Metrado Planificado Acumulado = lo que el cronograma/lookahead dice que ya deberia estar ejecutado a la fecha de corte. Metrado Ejecutado Acumulado = lo que el RDT reporta como realmente ejecutado (validado por Oficina Tecnica). Costo Real Acumulado = lo que de verdad costo ese avance (no siempre coincide con Metrado Ejecutado x Precio Unitario). Rendimiento Estandar (HH/Und) y HH Reales Acumuladas = insumos del IP (Indice de Productividad, ver hoja 3, ultimas 2 columnas).

Sheet 3. Ejemplo - Calculo EVM
A1: EJEMPLO APLICADO: CALCULO DE INDICADORES EVM
A2: Todas las celdas de esta hoja son formulas que leen la hoja '2. Datos Ficticios'. Cambia un dato alla y todo se recalcula aqui.
A4: Item | B4: Partida | C4: Monto contractual BAC ($/) | D4: PV ($/) (metr.plan. x P.U.) | E4: EV ($/) (metr.ejec. x P.U.) | F4: AC ($/) (Costo Real) | G4: CPI (EV/AC) | H4: SPI (EV/PV) | I4: % Avance Fisico (EV/BAC) | J4: HH Ganadas (metr.ejec. x Rendim.) | K4: IP (HH Ganadas/HH Reales acumuladas)
A5: ='2. Datos Ficticios'!A5 | B5: ='2. Datos Ficticios'!B5 | C5: ='2. Datos Ficticios'!D5*'2. Datos Ficticios'!E5 | D5: ='2. Datos Ficticios'!F5*'2. Datos Ficticios'!E5 | E5: ='2. Datos Ficticios'!G5*'2. Datos Ficticios'!E5 | F5: ='2. Datos Ficticios'!H5 | G5: =IFERROR(E5/F5,0) | H5: =IFERROR(E5/D5,0) | I5: =IFERROR(E5/C5,0) | J5: ='2. Datos Ficticios'!G5*'2. Datos Ficticios'!I5 | K5: =IFERROR(J5/'2. Datos Ficticios'!J5,0)
A6: ='2. Datos Ficticios'!A6 | B6: ='2. Datos Ficticios'!B6 | C6: ='2. Datos Ficticios'!D6*'2. Datos Ficticios'!E6 | D6: ='2. Datos Ficticios'!F6*'2. Datos Ficticios'!E6 | E6: ='2. Datos Ficticios'!G6*'2. Datos Ficticios'!E6 | F6: ='2. Datos Ficticios'!H6 | G6: =IFERROR(E6/F6,0) | H6: =IFERROR(E6/D6,0) | I6: =IFERROR(E6/C6,0) | J6: ='2. Datos Ficticios'!G6*'2. Datos Ficticios'!I6 | K6: =IFERROR(J6/'2. Datos Ficticios'!J6,0)
A7: ='2. Datos Ficticios'!A7 | B7: ='2. Datos Ficticios'!B7 | C7: ='2. Datos Ficticios'!D7*'2. Datos Ficticios'!E7 | D7: ='2. Datos Ficticios'!F7*'2. Datos Ficticios'!E7 | E7: ='2. Datos Ficticios'!G7*'2. Datos Ficticios'!E7 | F7: ='2. Datos Ficticios'!H7 | G7: =IFERROR(E7/F7,0) | H7: =IFERROR(E7/D7,0) | I7: =IFERROR(E7/C7,0) | J7: ='2. Datos Ficticios'!G7*'2. Datos Ficticios'!I7 | K7: =IFERROR(J7/'2. Datos Ficticios'!J7,0)
A8: ='2. Datos Ficticios'!A8 | B8: ='2. Datos Ficticios'!B8 | C8: ='2. Datos Ficticios'!D8*'2. Datos Ficticios'!E8 | D8: ='2. Datos Ficticios'!F8*'2. Datos Ficticios'!E8 | E8: ='2. Datos Ficticios'!G8*'2. Datos Ficticios'!E8 | F8: ='2. Datos Ficticios'!H8 | G8: =IFERROR(E8/F8,0) | H8: =IFERROR(E8/D8,0) | I8: =IFERROR(E8/C8,0) | J8: ='2. Datos Ficticios'!G8*'2. Datos Ficticios'!I8 | K8: =IFERROR(J8/'2. Datos Ficticios'!J8,0) | M8: Monto contractual BAC ($/) | N8: PV ($/) (metr.plan. x P.U.) | O8: EV ($/) (metr.ejec. x P.U.) | P8: AC ($/) (Costo Real) | Q8: CPI (EV/AC) | R8: SPI (EV/PV) | S8: % Avance Fisico (EV/BAC) | T8: HH Ganadas (metr.ejec. x Rendim.) | U8: IP (HH Ganadas/HH Reales acumuladas)
A9: ='2. Datos Ficticios'!A9 | B9: ='2. Datos Ficticios'!B9 | C9: ='2. Datos Ficticios'!D9*'2. Datos Ficticios'!E9 | D9: ='2. Datos Ficticios'!F9*'2. Datos Ficticios'!E9 | E9: ='2. Datos Ficticios'!G9*'2. Datos Ficticios'!E9 | F9: ='2. Datos Ficticios'!H9 | G9: =IFERROR(E9/F9,0) | H9: =IFERROR(E9/D9,0) | I9: =IFERROR(E9/C9,0) | J9: ='2. Datos Ficticios'!G9*'2. Datos Ficticios'!I9 | K9: =IFERROR(J9/'2. Datos Ficticios'!J9,0)
A10: ='2. Datos Ficticios'!A10 | B10: ='2. Datos Ficticios'!B10 | C10: ='2. Datos Ficticios'!D10*'2. Datos Ficticios'!E10 | D10: ='2. Datos Ficticios'!F10*'2. Datos Ficticios'!E10 | E10: ='2. Datos Ficticios'!G10*'2. Datos Ficticios'!E10 | F10: ='2. Datos Ficticios'!H10 | G10: =IFERROR(E10/F10,0) | H10: =IFERROR(E10/D10,0) | I10: =IFERROR(E10/C10,0) | J10: ='2. Datos Ficticios'!G10*'2. Datos Ficticios'!I10 | K10: =IFERROR(J10/'2. Datos Ficticios'!J10,0)
B11: TOTAL PROYECTO | C11: =SUM(C5:C10) | D11: =SUM(D5:D10) | E11: =SUM(E5:E10) | F11: =SUM(F5:F10) | G11: =IFERROR(E11/F11,0) | H11: =IFERROR(E11/D11,0) | I11: =IFERROR(E11/C11,0) | J11: =SUM(J5:J10) | K11: =IFERROR(J11/SUM('2. Datos Ficticios'!J5:'2. Datos Ficticios'!J10),0) | M11: Unid. | N11: Metrado | O11: Precio Unit. ($/) | P11: Metrado Planificado Acumulado (a la fecha) | Q11: Metrado Ejecutado Acumulado (real) | R11: Costo Real Acumulado ($/) | S11: Rendimiento (HH/Und) | T11: HH Reales Acumuladas
A12: El CPI, SPI, % Avance Fisico e IP del proyecto se calculan sobre los TOTALES (fila de arriba), nunca promediando el CPI/SPI/%/IP de cada partida por separado.
A14: RESUMEN - INDICADORES DEL PROYECTO
A15: BAC (Presupuesto Total) | E15: =C11
A16: PV (Valor Planificado) | E16: =D11
A17: EV (Valor Ganado) | E17: =E11
A18: AC (Costo Real) | E18: =F11
A19: CPI (Indice de Costo) | E19: =G11
A20: SPI (Indice de Cronograma) | E20: =H11
A21: IP (Indice de Productividad) | E21: =K11
A22: EAC = AC + (BAC-EV)/CPI | E22: =F11+(C11-E11)/G11
A23: VAC = BAC - EAC | E23: =C11-E22
A24: % Avance Fisico = EV / BAC | E24: =I11
A26: LECTURA AUTOMATICA (se actualiza sola con los datos)
A27: ="El CPI del proyecto es "&TEXT(G11,"0.00")&" -> "&IF(G11>=1,"por cada sol gastado se genero "&TEXT(G11,"0.00")&" soles de valor (eficiente).","por cada sol gastado solo se genero "&TEXT(G11,"0.00")&" soles de valor (se esta gastando de mas).")
A28: ="El SPI del proyecto es "&TEXT(H11,"0.00")&" -> "&IF(H11>=1,"el proyecto va adelantado o en linea con lo planificado (en valor).","el proyecto va atrasado respecto a lo planificado (en valor).")
A29: ="El avance fisico real del proyecto es "&TEXT(I11,"0.0%")&", calculado sobre el valor de cada partida (EV/BAC), no como promedio simple de los % de metrado."
A30: ="El IP del proyecto es "&TEXT(K11,"0.00")&" -> "&IF(K11>=1,"la mano de obra rinde igual o mejor que el estandar (HH ganadas >= HH reales).","la mano de obra rinde por debajo del estandar (se usaron mas HH reales que las HH ganadas).")
