Workbook
Name AC_Real_Acumulado: Ejercicio_Hibrido!$F$29
Name Avance_Planificado_Pct: Ejercicio_Hibrido!$F$30

Sheet RDO
A1: REPORTE DIARIO DE OBRA (RDO)
A2: Marcobre — Proyecto Movimiento de Tierras, Fabricación e Instalación de Bancoductos (EJEMPLO / DATOS FICTICIOS)
A4: DATOS GENERALES
A5: Contratista | B5: PROMCOSER | C5: Contrato N.º | D5: CT-2026-0458 | E5: CLIMA
A6: Ubicación | B6: Marcona | C6: Fecha de RDO | D6: 05/08/2026 | E6: T mín. | F6: 11°
A7: Fecha de Inicio | B7: 04/08/2026 | C7: RDO N.º | D7: 22 | E7: T máx. | F7: 24°
A8: Turno | B8: Día | C8: Régimen | D8: 6x1 | E8: Viento | F8: 15 Km/h
E9: Lluvia | F9: --
A10: RESUMEN EJECUTIVO DEL DÍA — se calcula solo, no se llena a mano
A11: Personal en obra hoy (headcount real, según Roster) | F11: =COUNTIF(Personal_Offsite!G3:G28,"A") | G11: personas
A12: HH trabajadas hoy (todas las actividades) | F12: =Actividades_Dia!H13 | G12: HH
A13: % Trabajo Productivo del día (Directo a partida) | F13: =Actividades_Dia!G17 | G13: %
A14: % Trabajo Contributorio del día | F14: =Actividades_Dia!G18 | G14: %
A15: % Trabajo No Contributorio del día | F15: =Actividades_Dia!G19 | G15: %
A16: Avance físico ponderado acumulado del proyecto | F16: =Partidas!M8 | G16: %
A17: Monto ejecutado acumulado (Venta a la fecha) | F17: =Partidas!O8 | G17: S/.
A18: Monto contractual total (Meta) | F18: =Partidas!G8 | G18: S/.
A19: HH Meta acumuladas (según avance ejecutado) | F19: =Partidas!P8 | G19: HH
A20: HH Reales acumuladas (solo directas a partida) | F20: =Partidas!S8 | G20: HH
A21: Índice de Productividad de MO (Meta / Real) | F21: =Partidas!U8 | G21: índice
A22: Restricciones abiertas | F22: =COUNTIF(Restricciones_Reuniones!G3:G5,"Abierta") | G22: und
A23: Cumplimiento control de alcohol y drogas | F23: =SSOMA_Calidad!E4 | G23: %
A25: ACTIVIDADES MÁS RELEVANTES DEL DÍA (texto libre corto, no reemplaza Partidas/Actividades_Dia)
A26: Se continúa excavación en PART-01 (tramo km 0+450), fabricación de bancoductos en cantera Marcona, izaje e instalación en Rampa Sur, vaciado de concreto en pedestal L-12 (Almacén Norte) y avance de montaje de estructura metálica columna C-08. Restricción activa: falta de tubería HDPE limita avance de PART-03.
A30: FIRMAS
A31: Reportado por: | E31: Revisado por:
A33: Ing. Residente PROMCOSER | E33: Supervisión AESA / Marcobre

Sheet Instrucciones
A1: CÓMO SE LLENA ESTE RDO
A3: PROPÓSITO: este archivo es la FUENTE PRIMARIA diaria de datos del proyecto. Todo lo que se necesita para el
A4: Cronograma, el Control de Costos / Resultado Operativo, Seguridad y Calidad sale de aquí — no de fotos sueltas ni de WhatsApp.
A6: ORDEN DE LLENADO (cada hoja alimenta a la siguiente — este es el cambio clave frente a la versión anterior):
A7: 1. Partidas — tabla maestra del proyecto: código, partida, área, unidad y metrado contractual. Se llena una vez
A8: al inicio del proyecto y casi no cambia día a día (solo el metrado acumulado de ayer, que se actualiza solo).
A9: 2. Actividades_Dia — QUÉ se hizo hoy: una fila por actividad (T1, T2, T3...), con su descripción, y muy importante,
A10: su CLASIFICACIÓN: 'D' (Directo a una partida), 'C' (Contributorio) o 'NC' (No Contributorio). Solo si es 'D' se
A11: liga a un código de Partidas y se anota el metrado ejecutado hoy.
A12: 3. Mano_Obra — QUIÉN trabajó y CUÁNTAS HORAS, ligado al código de actividad (T1, T2...) de Actividades_Dia, NO a la
A13: partida directamente. Un mismo trabajador puede aparecer en más de una fila si repartió su turno entre dos
A14: actividades (ej. 8h instalando + 2h en espera de material).
... A47: no información real del proyecto.

Sheet Mano_Obra
A1: MANO DE OBRA DEL DÍA — ligada a la ACTIVIDAD (T1, T2...), no directo a la partida
A2: Código Actividad | B2: Cargo | C2: Cant. | D2: HH/ persona | E2: HH Día | F2: Observaciones
A3: T1 | B3: Operador Excavadora | C3: 1 | D3: 10 | E3: =C3*D3
A4: T1 | B4: Ayudante | C4: 1 | D4: 10 | E4: =C4*D4
A5: T1 | B5: Vigía | C5: 1 | D5: 10 | E5: =C5*D5
B6: Subtotal T1 | C6: =SUM(C3:C5) | E6: =SUM(E3:E5)
A7: T2 | B7: Operario Civil | C7: 2 | D7: 10 | E7: =C7*D7
A8: T2 | B8: Oficial | C8: 3 | D8: 10 | E8: =C8*D8
A9: T2 | B9: Ayudante | C9: 2 | D9: 8 | E9: =C9*D9 | F9: Últimas 2h del turno -> T9 (orden y limpieza)
B10: Subtotal T2 | C10: =SUM(C7:C9) | E10: =SUM(E7:E9)
A11: T3 | B11: Operario Civil | C11: 1 | D11: 10 | E11: =C11*D11
A12: T3 | B12: Oficial | C12: 2 | D12: 10 | E12: =C12*D12
A13: T3 | B13: Operador Grúa | C13: 1 | D13: 8 | E13: =C13*D13 | F13: Últimas 2h del turno -> T8 (espera tubería HDPE)
B14: Subtotal T3 | C14: =SUM(C11:C13) | E14: =SUM(E11:E13)
A15: T4 | B15: Operario Civil | C15: 1 | D15: 10 | E15: =C15*D15
A16: T4 | B16: Oficial | C16: 2 | D16: 10 | E16: =C16*D16
A17: T4 | B17: Ayudante | C17: 1 | D17: 10 | E17: =C17*D17
B18: Subtotal T4 | C18: =SUM(C15:C17) | E18: =SUM(E15:E17)
A19: T5 | B19: Op. Mecánico / Eléctrico | C19: 1 | D19: 10 | E19: =C19*D19
A20: T5 | B20: Oficial | C20: 2 | D20: 10 | E20: =C20*D20
A21: T5 | B21: Ayudante | C21: 1 | D21: 10 | E21: =C21*D21
B22: Subtotal T5 | C22: =SUM(C19:C21) | E22: =SUM(E19:E21)
A23: T6 | B23: Cond. Camión Baranda | C23: 1 | D23: 10 | E23: =C23*D23 | F23: Transporte interno de materiales todo el turno
A24: T7 | B24: Personal operativo (23 pers.) | C24: 23 | D24: 0.5 | E24: =C24*D24 | F24: Charla previa al inicio de labores, todo el personal operativo
A25: T8 | B25: Operador Grúa | C25: 1 | D25: 2 | E25: =C25*D25 | F25: Mismo operador de T3, standby por falta de tubería HDPE (ver R-01)
A26: T9 | B26: Ayudante | C26: 2 | D26: 2 | E26: =C26*D26 | F26: Mismos 2 ayudantes de T2, orden y limpieza en cantera
A27: T10 | B27: Sup. Operativo | C27: 1 | D27: 10 | E27: =C27*D27
A28: T10 | B28: Sup. SSOMA | C28: 1 | D28: 10 | E28: =C28*D28
A29: T10 | B29: Ingeniero de Calidad | C29: 1 | D29: 10 | E29: =C29*D29
B30: Subtotal T10 | C30: =SUM(C27:C29) | E30: =SUM(E27:E29)
B31: TOTAL GENERAL DEL DÍA (HH-persona, no es headcount único) | C31: =SUMIF($A$3:$A$30,"<>",C3:C30) | E31: =SUMIF($A$3:$A$30,"<>",E3:E30)
A33: La columna Cant. suma bloques persona-actividad (una persona puede aparecer 2 veces). Para headcount real ver Personal_Offsite.

Sheet Actividades_Dia
A1: ACTIVIDADES DEL DÍA — qué se hizo, si fue directo a una partida, contributorio o no contributorio
A2: Código | B2: Descripción de la Actividad | C2: Clasif. (D/C/NC) | D2: Partida Asociada | E2: Área | F2: Und. | G2: Metrado Ejecutado Hoy | H2: HH Día | I2: Observaciones
A3: T1 | B3: Excavación de zanja para bancoductos - tramo km 0+450 | C3: D | D3: PART-01 | E3: Rampa Sur | F3: m3 | G3: 48 | H3: =SUMIF(Mano_Obra!$A$3:$A$30,A3,Mano_Obra!$E$3:$E$30)
A4: T2 | B4: Fabricación y curado de bancoductos prefabricados | C4: D | D4: PART-02 | E4: Cantera Marcona | F4: und | G4: 22 | H4: =SUMIF(Mano_Obra!$A$3:$A$30,A4,Mano_Obra!$E$3:$E$30)
A5: T3 | B5: Izaje e instalación de bancoductos con grúa | C5: D | D5: PART-03 | E5: Rampa Sur | F5: ml | G5: 12 | H5: =SUMIF(Mano_Obra!$A$3:$A$30,A5,Mano_Obra!$E$3:$E$30)
A6: T4 | B6: Vaciado de concreto f'c=210 - pedestal L-12 | C6: D | D6: PART-04 | E6: Almacén Norte | F6: m3 | G6: 6 | H6: =SUMIF(Mano_Obra!$A$3:$A$30,A6,Mano_Obra!$E$3:$E$30)
A7: T5 | B7: Montaje de estructura metálica - columna C-08 | C7: D | D7: PART-05 | E7: Almacén Norte | F7: kg | G7: 300 | H7: =SUMIF(Mano_Obra!$A$3:$A$30,A7,Mano_Obra!$E$3:$E$30)
A8: T6 | B8: Transporte interno de materiales y herramientas | C8: C | D8: -- | E8: Varios frentes | F8: -- | H8: =SUMIF(Mano_Obra!$A$3:$A$30,A8,Mano_Obra!$E$3:$E$30)
A9: T7 | B9: Charla de seguridad e instrucciones de trabajo | C9: C | D9: -- | E9: Varios frentes | F9: -- | H9: =SUMIF(Mano_Obra!$A$3:$A$30,A9,Mano_Obra!$E$3:$E$30)
A10: T8 | B10: Espera de tubería HDPE (grúa parada) | C10: NC | D10: -- | E10: Rampa Sur | F10: -- | H10: =SUMIF(Mano_Obra!$A$3:$A$30,A10,Mano_Obra!$E$3:$E$30) | I10: Vinculado a restricción R-01
A11: T9 | B11: Orden y limpieza de zona de trabajo | C11: C | D11: -- | E11: Cantera Marcona | F11: -- | H11: =SUMIF(Mano_Obra!$A$3:$A$30,A11,Mano_Obra!$E$3:$E$30)
A12: T10 | B12: Supervisión, control de calidad y SSOMA | C12: C | D12: -- | E12: Varios frentes | F12: -- | H12: =SUMIF(Mano_Obra!$A$3:$A$30,A12,Mano_Obra!$E$3:$E$30)
B13: TOTAL | H13: =SUM(H3:H12)
A15: RESUMEN NIVEL GENERAL DE ACTIVIDAD (Last Planner: TP / TC / TNC)
A16: Clasificación | D16: HH | G16: % del día
A17: Directo (Trabajo Productivo) | D17: =SUMIF($C$3:$C$12,"D",$H$3:$H$12) | G17: =D17/H13
A18: Contributorio | D18: =SUMIF($C$3:$C$12,"C",$H$3:$H$12) | G18: =D18/H13
A19: No Contributorio | D19: =SUMIF($C$3:$C$12,"NC",$H$3:$H$12) | G19: =D19/H13

Sheet Partidas
A1: PARTIDAS DEL PROYECTO — catálogo, avance físico y rendimiento de mano de obra
A2: Código | B2: Partida | C2: Área | D2: Und. | E2: Metrado Contractual | F2: P.U. (S/.) | G2: Monto Contractual (S/.) | H2: Rendim. Meta (HH/Und) | I2: Metrado Acum. Anterior | J2: Metrado Prog. Día | K2: Metrado Ejec. Día | L2: Metrado Acum. Actual | M2: % Avance Acum. | N2: Por Ejecutar | O2: Monto Ejec. Acum. (Venta) (S/.) | P2: HH Meta Acum. | Q2: HH Real Acum. Anterior | R2: HH Real Día | S2: HH Real Acum. Actual | T2: Rendim. Real (HH/Und) | U2: Índice Product. MO
A3: PART-01 | B3: Excavación para bancoductos | C3: Rampa Sur | D3: m3 | E3: 1200 | F3: 18.5 | G3: =E3*F3 | H3: 0.35 | I3: 640 | J3: 45 | K3: =SUMIF(Actividades_Dia!$D$3:$D$12,$A3,Actividades_Dia!$G$3:$G$12) | L3: =I3+K3 | M3: =L3/E3 | N3: =E3-L3 | O3: =L3*F3 | P3: =L3*H3 | Q3: 225 | R3: =SUMIF(Actividades_Dia!$D$3:$D$12,$A3,Actividades_Dia!$H$3:$H$12) | S3: =Q3+R3 | T3: =S3/L3 | U3: =P3/S3
A4: PART-02 | B4: Fabricación de bancoductos 0.20x0.20x1.00m | C4: Cantera Marcona | D4: und | E4: 400 | F4: 145 | G4: =E4*F4 | H4: 2.8 | I4: 120 | J4: 20 | K4: =SUMIF(Actividades_Dia!$D$3:$D$12,$A4,Actividades_Dia!$G$3:$G$12) | L4: =I4+K4 | M4: =L4/E4 | N4: =E4-L4 | O4: =L4*F4 | P4: =L4*H4 | Q4: 310 | R4: =SUMIF(Actividades_Dia!$D$3:$D$12,$A4,Actividades_Dia!$H$3:$H$12) | S4: =Q4+R4 | T4: =S4/L4 | U4: =P4/S4
A5: PART-03 | B5: Instalación de bancoductos | C5: Rampa Sur | D5: ml | E5: 600 | F5: 95 | G5: =E5*F5 | H5: 3.2 | I5: 80 | J5: 15 | K5: =SUMIF(Actividades_Dia!$D$3:$D$12,$A5,Actividades_Dia!$G$3:$G$12) | L5: =I5+K5 | M5: =L5/E5 | N5: =E5-L5 | O5: =L5*F5 | P5: =L5*H5 | Q5: 270 | R5: =SUMIF(Actividades_Dia!$D$3:$D$12,$A5,Actividades_Dia!$H$3:$H$12) | S5: =Q5+R5 | T5: =S5/L5 | U5: =P5/S5
A6: PART-04 | B6: Vaciado de concreto f'c=210 kg/cm2 | C6: Almacén Norte | D6: m3 | E6: 85 | F6: 380 | G6: =E6*F6 | H6: 6.5 | I6: 22 | J6: 6 | K6: =SUMIF(Actividades_Dia!$D$3:$D$12,$A6,Actividades_Dia!$G$3:$G$12) | L6: =I6+K6 | M6: =L6/E6 | N6: =E6-L6 | O6: =L6*F6 | P6: =L6*H6 | Q6: 155 | R6: =SUMIF(Actividades_Dia!$D$3:$D$12,$A6,Actividades_Dia!$H$3:$H$12) | S6: =Q6+R6 | T6: =S6/L6 | U6: =P6/S6
A7: PART-05 | B7: Montaje de estructuras metálicas | C7: Almacén Norte | D7: kg | E7: 12000 | F7: 8.2 | G7: =E7*F7 | H7: 0.45 | I7: 3100 | J7: 350 | K7: =SUMIF(Actividades_Dia!$D$3:$D$12,$A7,Actividades_Dia!$G$3:$G$12) | L7: =I7+K7 | M7: =L7/E7 | N7: =E7-L7 | O7: =L7*F7 | P7: =L7*H7 | Q7: 1450 | R7: =SUMIF(Actividades_Dia!$D$3:$D$12,$A7,Actividades_Dia!$H$3:$H$12) | S7: =Q7+R7 | T7: =S7/L7 | U7: =P7/S7
B8: TOTAL PROYECTO | E8: =SUM(E3:E7) | G8: =SUM(G3:G7) | I8: =SUM(I3:I7) | J8: =SUM(J3:J7) | K8: =SUM(K3:K7) | L8: =SUM(L3:L7) | M8: =O8/G8 | O8: =SUM(O3:O7) | P8: =SUM(P3:P7) | Q8: =SUM(Q3:Q7) | R8: =SUM(R3:R7) | S8: =SUM(S3:S7) | T8: =S8/L8 | U8: =P8/S8
A10: Amarillo = captura manual (metrado acumulado de ayer, programado de hoy, HH real acumulada de ayer). El resto se calcula solo, jalando de Actividades_Dia.

Sheet Equipos
A1: HISTOGRAMA DE EQUIPOS DEL DÍA
A2: Equipo | B2: Código Partida | C2: Estado | D2: HH Turno Día | E2: HH Acum. Anterior | F2: HH Acum. Actual | G2: Observaciones
A3: Retroexcavadora | B3: PART-01 | C3: Operativo | D3: 8.5 | E3: 137 | F3: =E3+D3
A4: Minicargador | B4: PART-01 | C4: Operativo | D4: 6.5 | E4: 91.5 | F4: =E4+D4
A5: Compactadora de plancha | B5: PART-01 | C5: Operativo | D5: 3 | E5: 19 | F5: =E5+D5
A6: Grúa telescópica 25T | B6: PART-03 | C6: Operativo | D6: 5 | E6: 57 | F6: =E6+D6 | G6: Con tiempos muertos por falta de tubería (ver R-01)
A7: Camión grúa | B7: PART-05 | C7: Operativo | D7: 4.5 | E7: 35.5 | F7: =E7+D7
A8: Vibrador de concreto | B8: PART-04 | C8: Operativo | D8: 4 | E8: 26 | F8: =E8+D8
A9: Equipo de soldar | B9: PART-05 | C9: Operativo | D9: 6 | E9: 44 | F9: =E9+D9
A10: TOTAL | D10: =SUM(D3:D9) | F10: =SUM(F3:F9)

Sheet Materiales
A1: CONSUMO DE MATERIALES DEL DÍA
A2: Insumo | B2: Unidad | C2: Código Partida | D2: Consumo Día | E2: Consumo Acum. Anterior | F2: Consumo Acum. Actual | G2: Saldo en Stock | H2: Observaciones
A3: Cemento Tipo I | B3: bls | C3: PART-04 | D3: 45 | E3: 165 | F3: =E3+D3 | G3: 180
A4: Fierro corrugado 3/8" | B4: kg | C4: PART-04 | D4: 850 | E4: 3350 | F4: =E4+D4 | G4: 3100
A5: Tubería HDPE para bancoducto | B5: ml | C5: PART-03 | D5: 12 | E5: 80 | F5: =E5+D5 | G5: 8 | H5: Stock crítico — ver restricción R-01
A6: Electrodos de soldadura 6011 | B6: kg | C6: PART-05 | D6: 15 | E6: 195 | F6: =E6+D6 | G6: 90
A7: Encofrado metálico (uso propio) | B7: m2 | C7: PART-04 | D7: 0 | E7: 0 | F7: =E7+D7 | G7: -- | H7: No es consumible, no aplica saldo
A9: ENTREGAS / RECEPCIONES DEL DÍA
A10: Proveedor | B10: Material | C10: Cantidad | D10: Unidad | E10: Hora Prog. | F10: Hora Real | G10: Guía / Remisión N° | H10: Recibido por
A11: Ferretería Marcona SAC | B11: Cemento Tipo I | C11: 100 | D11: bls | E11: 09:00 | F11: 09:40 | G11: GR-004521 | H11: J. Torres (Almacenero)
A12: Aceros Arequipa - Distribuidor local | B12: Fierro corrugado 3/8" | C12: 1000 | D12: kg | E12: 11:00 | F12: 11:15 | G12: GR-008832 | H12: J. Torres (Almacenero)

Sheet SSOMA_Calidad
A1: SEGURIDAD (SSOMA)
A2: Control de Alcohol y Drogas
A3: N° Programados | B3: N° Evaluados | C3: N° Positivos | D3: N° Negativos | E3: % Cumplimiento
A4: 26 | B4: 26 | C4: 0 | D4: 26 | E4: =B4/A4
A6: Charlas de Seguridad
A7: Hora | B7: Tema | C7: Responsable | D7: N° Asistentes | E7: Duración (min)
A8: 06:30 | B8: Trabajos en caliente - soldadura y esmerilado | C8: Sup. SSOMA | D8: 23 | E8: 15
A9: 06:45 | B9: Buenos Días Mina Justa (BDMJ) - Uso correcto de EPP | C9: Sup. SSOMA | D9: 23 | E9: 10
A11: Inspecciones
A12: N° | B12: Área / Partida | C12: Hallazgo | D12: Riesgo | E12: Estado | F12: Responsable | G12: Fecha Cierre
A13: INS-01 | B13: PART-01 (Excavación) | C13: Falta de señalización perimetral en talud | D13: Medio | E13: Cerrado | F13: Sup. SSOMA | G13: 05/08/2026
A14: INS-02 | B14: PART-05 (Montaje) | C14: Amarre de andamio insuficiente | D14: Alto | E14: Cerrado | F14: Sup. SSOMA | G14: 05/08/2026
A15: INS-03 | B15: Almacén Norte | C15: Orden y limpieza deficiente en zona de acopio | D15: Bajo | E15: Abierto | F15: Sup. Operativo | G15: Pendiente
A17: Incidentes / Casi Accidentes
A18: N° | B18: Tipo | C18: Descripción | D18: Partida | E18: Severidad | F18: Acción Tomada
A19: CA-01 | B19: Casi accidente | C19: Caída de material menor desde andamio, sin lesionados | D19: PART-05 | E19: Leve | F19: Charla de refuerzo de amarre de herramientas y materiales en altura
A21: CALIDAD
A22: Ensayos
A23: N° | B23: Tipo de Ensayo | C23: Partida | D23: Resultado | E23: Estado
A24: EN-01 | B24: Prueba de asentamiento (slump) | C24: PART-04 | D24: 4 pulgadas | E24: Conforme
A25: EN-02 | B25: Ensayo de compresión - probetas 7 días | C25: PART-04 | D25: Programado 12/08/2026 | E25: Pendiente
A27: No Conformidades
A28: N° | B28: Descripción | C28: Partida | D28: Responsable | E28: Estado | F28: Fecha Límite
A29: NC-014 | B29: Recubrimiento de bancoducto fuera de tolerancia especificada | C29: PART-02 | D29: Ing. Calidad | E29: Abierta | F29: 08/08/2026
A31: Liberaciones
A32: N° | B32: Elemento | C32: Partida | D32: Aprobado por | E32: Resultado
A33: LIB-09 | B33: Encofrado y acero de pedestal L-12 | C33: PART-04 | D33: Ing. Calidad (V. Pérez Contreras) | E33: Liberado para vaciado

Sheet Restricciones_Reuniones
A1: RESTRICCIONES / INTERFERENCIAS (compromisos tipo Last Planner)
A2: N° | B2: Restricción | C2: Partida Afectada | D2: Responsable | E2: Atribuible a | F2: Fecha Compromiso | G2: Estado | H2: Impacto (días)
A3: R-01 | B3: Falta de tubería HDPE para completar instalación | C3: PART-03 | D3: Logística PROMCOSER | E3: PROMCOSER | F3: 07/08/2026 | G3: Abierta | H3: 2
A4: R-02 | B4: Aprobación de diseño de pedestal pendiente por cliente | C4: PART-04 | D4: Oficina Técnica | E4: Cliente (Marcobre) | F4: 06/08/2026 | G4: Abierta | H4: 1
A5: R-03 | B5: Interferencia con tendido eléctrico existente en zona de excavación | C5: PART-01 | D5: Ing. Residente | E5: AESA | F5: 04/08/2026 | G5: Cerrada | H5: 0
A7: REUNIONES
A8: Hora | B8: Tipo | C8: Asistentes | D8: Temas Tratados | E8: Acuerdos
A9: 07:00 | B9: Charla de inicio + coordinación diaria | C9: 23 | D9: Plan del día, riesgos en PART-05 (trabajos en altura) | E9: Reforzar señalización en excavación PART-01
A10: 15:30 | B10: Coordinación con supervisión AESA | C10: 4 | D10: Avance de la semana, restricción de tubería HDPE | E10: AESA gestiona compra urgente de tubería
A12: VISITANTES
A13: Nombre | B13: Empresa | C13: Motivo | D13: Hora Ingreso | E13: Hora Salida
A14: Ing. Carlos Ramos Dávila | B14: AESA (Supervisión) | C14: Inspección de avance de obra | D14: 10:00 | E14: 11:30
A15: Ing. Lucía Fernández Soto | B15: Marcobre (Cliente) | C15: Visita de verificación SSOMA | D15: 14:00 | E15: 14:45

Sheet Fotos
A1: REGISTRO FOTOGRÁFICO DEL DÍA
A2: N° | B2: Código Partida | C2: Frente / Ubicación | D2: Descripción | E2: Fotografía
A3: 1 | B3: PART-01 | C3: Excavación bancoductos | D3: Avance de excavación tramo km 0+450 | E3: [Insertar fotografía aquí]
A4: 2 | B4: PART-02 | C4: Cantera Marcona | D4: Curado y limpieza de bancoductos prefabricados | E4: [Insertar fotografía aquí]
A5: 3 | B5: PART-03 | C5: Rampa Sur | D5: Izaje e instalación de bancoducto con grúa | E5: [Insertar fotografía aquí]
A6: 4 | B6: PART-04 | C6: Almacén Norte | D6: Vaciado de concreto f'c=210 en pedestal L-12 | E6: [Insertar fotografía aquí]
A7: 5 | B7: PART-05 | C7: Almacén Norte | D7: Montaje de estructura metálica - columna C-08 | E7: [Insertar fotografía aquí]

Sheet Personal_Offsite
A1: ROSTER NOMINAL DEL DÍA — fuente oficial de headcount (Mano_Obra es por actividad, no por persona única)
A2: N° | B2: DNI | C2: Apellidos y Nombres | D2: Cargo | E2: Actividad Principal | F2: Condición | G2: Asistencia
A3: 1 | B3: 71234567 | C3: RAMOS QUISPE, Jhonny | D3: Operador Excavadora | E3: T1 | F3: Activo | G3: A
A4: 2 | B4: 72345678 | C4: HUARANCCA TORRES, Elmer | D4: Ayudante | E4: T1 | F4: Activo | G4: A
A5: 3 | B5: 73456789 | C5: PACHECO LIMA, Rosa | D5: Vigía | E5: T1 | F5: Activo | G5: A
A6: 4 | B6: 73095782 | C6: BARDALES TRUJILLO, Sandro Luis | D6: Operario Civil | E6: T2 | F6: Activo | G6: A
A7: 5 | B7: 75715613 | C7: ALVAREZ CRESPO, Moises Juan | D7: Operario Civil | E7: T2 | F7: Activo | G7: A
A8: 6 | B8: 76891111 | C8: FARIAS ULFE, Joshua Manuel Humberto | D8: Oficial | E8: T2 | F8: Activo | G8: A
A9: 7 | B9: 71831041 | C9: ROMUCHO HUAMAN, Porfirio Jose | D9: Oficial | E9: T2 | F9: Activo | G9: A
A10: 8 | B10: 73261821 | C10: CASTRO LEON, Abran | D10: Oficial | E10: T2 | F10: Activo | G10: A
A11: 9 | B11: 60741098 | C11: ALVARADO AGREDA, Ronald Martin | D11: Ayudante | E11: T2 / T9 | F11: Activo | G11: A
A12: 10 | B12: 74562849 | C12: COTRINA ALTAMIRANO, Jose Alfredo | D12: Ayudante | E12: T2 / T9 | F12: Activo | G12: A
A13: 11 | B13: 70521512 | C13: CAYO GUTIERREZ, Juan Wilfredo | D13: Operario Civil | E13: T3 | F13: Activo | G13: A
A14: 12 | B14: 43141186 | C14: GARRIAZO OSCO, Richard Felix | D14: Oficial | E14: T3 | F14: Activo | G14: A
... A28: 26 | B28: 41531893 | C28: PEREZ CONTRERA, Victor Raul | D28: Ingeniero de Calidad | E28: T10 | F28: Activo | G28: A

Sheet Ejercicio_Hibrido
A1: EJERCICIO — RDT (otro archivo) → RDO: trazabilidad real + parámetros únicos para EVM
A3: Verde = viene POR FÓRMULA de otro archivo (RDT_Ejemplo_Relleno.xlsx). Azul = viene de la hoja Partidas (mismo archivo). Amarillo = parámetro único con nombre — cámbialo y todo lo que depende de él se recalcula solo. Si Excel te pregunta 'Actualizar vínculos' al abrir este archivo, dile que sí (es normal en archivos vinculados).
A5: AVANCE FÍSICO Y PRODUCTIVIDAD DEL DÍA
A6: Código | B6: Partida | C6: Und. | D6: Metrado Contractual | E6: P.U. (S/.) | F6: Monto Contractual (BAC) (S/.) | G6: Rendim. Meta (HH/Und) | H6: Metrado Acum. Anterior (=Partidas!L) | I6: Metrado Prog. Día (=RDT) | J6: Metrado Ejec. Día (=RDT) | K6: ¿Cumplió programa? (PPC) | L6: Metrado Acum. Actual | M6: % Avance Físico Acum. | N6: Monto Ejec. Acum. = EV (S/.) | O6: HH Meta Acum. | P6: HH Real Acum. Anterior (=Partidas!S) | Q6: HH Real Día (=RDT, puente) | R6: HH Real Acum. Actual | S6: Rendim. Real (HH/Und) | T6: Índice Product. MO
A7: PART-01 | B7: Excavación para bancoductos | C7: m3 | D7: 1200 | E7: 18.5 | F7: =D7*E7 | G7: 0.35 | H7: =Partidas!L3 | I7: =SUMIF('[RDT_Ejemplo_Relleno.xlsx]RDT'!$N$12:$N$19,$A7,'[RDT_Ejemplo_Relleno.xlsx]RDT'!$Q$12:$Q$19) | J7: =SUMIF('[RDT_Ejemplo_Relleno.xlsx]RDT'!$N$12:$N$19,$A7,'[RDT_Ejemplo_Relleno.xlsx]RDT'!$R$12:$R$19) | K7: =IF(J7>=I7,"SI","NO") | L7: =H7+J7 | M7: =L7/D7 | N7: =L7*E7 | O7: =L7*G7 | P7: =Partidas!S3 | Q7: =SUMIF($B$16:$B$23,$A7,$C$16:$C$23) | R7: =P7+Q7 | S7: =R7/L7 | T7: =O7/R7
A8: PART-02 | B8: Fabricación de bancoductos 0.20x0.20x1.00m | C8: und | D8: 400 | E8: 145 | F8: =D8*E8 | G8: 2.8 | H8: =Partidas!L4 | I8: =SUMIF('[RDT_Ejemplo_Relleno.xlsx]RDT'!$N$12:$N$19,$A8,'[RDT_Ejemplo_Relleno.xlsx]RDT'!$Q$12:$Q$19) | J8: =SUMIF('[RDT_Ejemplo_Relleno.xlsx]RDT'!$N$12:$N$19,$A8,'[RDT_Ejemplo_Relleno.xlsx]RDT'!$R$12:$R$19) | K8: =IF(J8>=I8,"SI","NO") | L8: =H8+J8 | M8: =L8/D8 | N8: =L8*E8 | O8: =L8*G8 | P8: =Partidas!S4 | Q8: =SUMIF($B$16:$B$23,$A8,$C$16:$C$23) | R8: =P8+Q8 | S8: =R8/L8 | T8: =O8/R8
A9: PART-03 | B9: Instalación de bancoductos | C9: ml | D9: 600 | E9: 95 | F9: =D9*E9 | G9: 3.2 | H9: =Partidas!L5 | I9: =SUMIF('[RDT_Ejemplo_Relleno.xlsx]RDT'!$N$12:$N$19,$A9,'[RDT_Ejemplo_Relleno.xlsx]RDT'!$Q$12:$Q$19) | J9: =SUMIF('[RDT_Ejemplo_Relleno.xlsx]RDT'!$N$12:$N$19,$A9,'[RDT_Ejemplo_Relleno.xlsx]RDT'!$R$12:$R$19) | K9: =IF(J9>=I9,"SI","NO") | L9: =H9+J9 | M9: =L9/D9 | N9: =L9*E9 | O9: =L9*G9 | P9: =Partidas!S5 | Q9: =SUMIF($B$16:$B$23,$A9,$C$16:$C$23) | R9: =P9+Q9 | S9: =R9/L9 | T9: =O9/R9
A10: PART-04 | B10: Vaciado de concreto f'c=210 kg/cm2 | C10: m3 | D10: 85 | E10: 380 | F10: =D10*E10 | G10: 6.5 | H10: =Partidas!L6 | I10: =SUMIF('[RDT_Ejemplo_Relleno.xlsx]RDT'!$N$12:$N$19,$A10,'[RDT_Ejemplo_Relleno.xlsx]RDT'!$Q$12:$Q$19) | J10: =SUMIF('[RDT_Ejemplo_Relleno.xlsx]RDT'!$N$12:$N$19,$A10,'[RDT_Ejemplo_Relleno.xlsx]RDT'!$R$12:$R$19) | K10: =IF(J10>=I10,"SI","NO") | L10: =H10+J10 | M10: =L10/D10 | N10: =L10*E10 | O10: =L10*G10 | P10: =Partidas!S6 | Q10: =SUMIF($B$16:$B$23,$A10,$C$16:$C$23) | R10: =P10+Q10 | S10: =R10/L10 | T10: =O10/R10
A11: PART-05 | B11: Montaje de estructuras metálicas | C11: kg | D11: 12000 | E11: 8.2 | F11: =D11*E11 | G11: 0.45 | H11: =Partidas!L7 | I11: =SUMIF('[RDT_Ejemplo_Relleno.xlsx]RDT'!$N$12:$N$19,$A11,'[RDT_Ejemplo_Relleno.xlsx]RDT'!$Q$12:$Q$19) | J11: =SUMIF('[RDT_Ejemplo_Relleno.xlsx]RDT'!$N$12:$N$19,$A11,'[RDT_Ejemplo_Relleno.xlsx]RDT'!$R$12:$R$19) | K11: =IF(J11>=I11,"SI","NO") | L11: =H11+J11 | M11: =L11/D11 | N11: =L11*E11 | O11: =L11*G11 | P11: =Partidas!S7 | Q11: =SUMIF($B$16:$B$23,$A11,$C$16:$C$23) | R11: =P11+Q11 | S11: =R11/L11 | T11: =O11/R11
B12: TOTAL PROYECTO | D12: =SUM(D7:D11) | F12: =SUM(F7:F11) | H12: =SUM(H7:H11) | I12: =SUM(I7:I11) | J12: =SUM(J7:J11) | L12: =SUM(L7:L11) | M12: =N12/F12 | N12: =SUM(N7:N11) | O12: =SUM(O7:O11) | P12: =SUM(P7:P11) | Q12: =SUM(Q7:Q11) | R12: =SUM(R7:R11) | S12: =R12/L12 | T12: =O12/R12
A14: PUENTE RDT → RDO (trazabilidad entre archivos)
A15: Ítem (T1..T8) | B15: WBS (=RDT, Avance) | C15: HH Total del día (=RDT, suma Tareo)
A16: T1 | B16: ='[RDT_Ejemplo_Relleno.xlsx]RDT'!N12 | C16: =SUM('[RDT_Ejemplo_Relleno.xlsx]RDT'!J24:J39)
A17: T2 | B17: ='[RDT_Ejemplo_Relleno.xlsx]RDT'!N13 | C17: =SUM('[RDT_Ejemplo_Relleno.xlsx]RDT'!K24:K39)
A18: T3 | B18: ='[RDT_Ejemplo_Relleno.xlsx]RDT'!N14 | C18: =SUM('[RDT_Ejemplo_Relleno.xlsx]RDT'!L24:L39)
A19: T4 | B19: ='[RDT_Ejemplo_Relleno.xlsx]RDT'!N15 | C19: =SUM('[RDT_Ejemplo_Relleno.xlsx]RDT'!M24:M39)
A20: T5 | B20: ='[RDT_Ejemplo_Relleno.xlsx]RDT'!N16 | C20: =SUM('[RDT_Ejemplo_Relleno.xlsx]RDT'!N24:N39)
A21: T6 | B21: ='[RDT_Ejemplo_Relleno.xlsx]RDT'!N17 | C21: =SUM('[RDT_Ejemplo_Relleno.xlsx]RDT'!O24:O39)
A22: T7 | B22: ='[RDT_Ejemplo_Relleno.xlsx]RDT'!N18 | C22: =SUM('[RDT_Ejemplo_Relleno.xlsx]RDT'!P24:P39)
A23: T8 | B23: ='[RDT_Ejemplo_Relleno.xlsx]RDT'!N19 | C23: =SUM('[RDT_Ejemplo_Relleno.xlsx]RDT'!Q24:Q39)
A24: Columna WBS: se lee directo de la fila de ese ítem en 2.0 Reporte de Avance del RDT. Columna HH Total: se suma directo de la columna de ese ítem en 3.0 Tareo Personal del RDT (filas 24 a 39, los trabajadores). Con esas dos columnas alineadas aquí, arriba se puede hacer un SUMIF normal por WBS — sin fórmulas de matriz.
A27: PARÁMETROS DE ENTRADA (los dos datos que faltan — cámbialos y mira qué se mueve)
A28: Nombre del dato | F28: Valor | G28: Fuente real (todavía no existe)
A29: AC_Real_Acumulado — Costo Real Acumulado del Proyecto (S/.) | F29: 89000 | G29: Planilla de costos (HH × costo-hora cargado) + materiales + equipos — no capturado hoy
A30: Avance_Planificado_Pct — % Avance Planificado Acumulado (curva S / cronograma valorizado) | F30: 0.34 | G30: Cronograma valorizado (baseline) — no existe todavía en ningún RDT/RDO
A32: TABLERO DE KPIs — SISTEMA HÍBRIDO EVM + LPS
A33: BAC — Presupuesto total | G33: =F12
A34: PV — Valor Planificado acumulado (=BAC × Avance_Planificado_Pct) | G34: =F12*Avance_Planificado_Pct | H34: (depende del parámetro de arriba)
A35: EV — Valor Ganado acumulado (Venta) | G35: =N12
A36: AC — Costo Real acumulado (=AC_Real_Acumulado) | G36: =AC_Real_Acumulado | H36: (depende del parámetro de arriba)
A37: SV = EV - PV | G37: =N12-F12*Avance_Planificado_Pct | H37: (depende del parámetro de arriba)
A38: CV = EV - AC | G38: =N12-AC_Real_Acumulado | H38: (depende del parámetro de arriba)
A39: SPI = EV / PV | G39: =N12/(F12*Avance_Planificado_Pct) | H39: (depende del parámetro de arriba)
A40: CPI = EV / AC | G40: =N12/AC_Real_Acumulado | H40: (depende del parámetro de arriba)
A41: EAC = BAC / CPI (proyección al cierre) | G41: =F12/(N12/AC_Real_Acumulado) | H41: (depende del parámetro de arriba)
A42: VAC = BAC - EAC | G42: =F12-(F12/(N12/AC_Real_Acumulado)) | H42: (depende del parámetro de arriba)
A44: % Avance físico acumulado (EV/BAC) | G44: =N12/F12
A45: Índice de Productividad MO global (HH Meta/HH Real) | G45: =O12/R12
A46: % PPC (partidas que cumplieron lo programado hoy) | G46: =COUNTIF(K7:K11,"SI")/COUNTA(K7:K11)
A49: AHORA la trazabilidad es completa en dos niveles: (1) entre archivos — Prog./Ejec./HH del día se leen en vivo del RDT_Ejemplo_Relleno.xlsx, cambia un número ahí y se mueve todo aquí; (2) dentro del RDO — AC y % Avance Planificado son dos celdas únicas y nombradas (Parámetros de Entrada), cambia cualquiera de las dos y se recalculan solos SV, CV, SPI, CPI, EAC y VAC. Esos dos parámetros siguen siendo el único dato que hoy no sale de ningún RDT/RDO real — hay que decidir de dónde los vamos a sacar de verdad (costos y cronograma valorizado).
