Workbook
Name Print_Area: APU!$A$1:$F$768
Name Print_Area: CD!$A$1:$H$70
Name Print_Area: GG!$A$1:$I$75
Name Print_Area: METRADO!$A$1:$E$44
Name Print_Area: PRESUPUESTO!$A$1:$V$125
Name Print_Area: 'PS..'!$A$1:$H$51

Sheet PRESUPUESTO
Q2: Presupuesto / Budget Nº | R2: PS-065-2026 PROMCOSER
Q4: Fecha / Date: | R4: 46216
B5: RUC: 20494224314
B6: Mza Ñ lote.3 AH Micaela Bastidas- Marcona
B7: Teléfono: 056-525092
B8: 1.- Cliente / customer
B9: Nombre / Name: | E9: AESA | O9: RUC / VAT ID No.:
B10: Dirección / Address: | E10: AESA | P10: Teléf.. Fax:
B11: Att.:
B12: Proyecto / Project: | E12: PROYECTO: MOV. TIERRAS, FAB. E INSTALACIÓN DE BANCODUCTOS
B15: 2.- Alcances y Condiciones / Conditions
C17: Servicio especializado para infraestructura minera
B22: 3.- Precio y Descripción:
B23: Ítem | C23: Descripción / Descripción | O23: Unid | P23: Cantidad | R23: Precio Unit. | T23: Total
P24: QTY | R24: Unit Price
R25: $ | T25: $
C26: =E12 -> PROYECTO: MOV. TIERRAS, FAB. E INSTALACIÓN DE BANCODUCTOS | O26: GLB | P26: 1 | R26: =CD!H70 -> 123807.96 | T26: =+R26*P26 -> 123807.96
S32: Total $ | T32: =+T26 -> 123807.96
B33: Son: | C33: CIENTO SETENTA Y UN MIL CUATROCIENTOS CUARENTA Y DOS CON 56/100 DOLARES AMERICANOS | R33: Gastos Generales | S33: =T33/T32 -> 0.22029169 | T33: =GG!I74 -> 27273.865
R34: Combustible (Reembolsable) | T34: =COMBUSTIBLE!H12 -> 7979.94
C35: No incluye IGV | R35: Utilidad | S35: 0.1 | T35: =+T32*S35 -> 12380.796
R36: Total sin IGV | S36: USD | T36: =+T35+T33+T32+T34 -> 171442.56
B39: 4.- Condiciones de Compra / Terms of Purchase
B41: Moneda/Currency: | E41: =+T36 -> 171442.56 | H41: Soles [S/.] | K41: X | L41: Dólares Americanos [USD] | Q41: Otro:
B43: Tipo de Servicio / Type of Service | G43: x | H43: Suma Alzada | L43: Otro: | M43: Suma Alzada
B45: Forma de Pago/Form of Payment: | G45: PAGO ANTICIPADO O PREVIO ACUERDO
B47: Tiempo de entrega / Delivery time: | G47: 45 días
B49: Validez de Oferta/Validity of Offer: | G49: 15 Días Calendarios
B51: Lugar / Place | G51: MINA JUSTA - MARCOBRE
B53: Garantía / Warranty | G53: : PROMCOSER garantiza la calidad de los trabajos realizados corrigiendo o reparando los trabajos defectuosos
G54: que sean imputables a PROMCOSER.
B56: Hecho por / Handled by: | F56: A. Cuellar | K56: e-mail: | L56: ventas@promcoser.com.pe | Q56: T.Movil: | R56: 940512282
Q59: Presupuesto / Budget Nº | R59: =+R2 -> PS-065-2026 PROMCOSER
Q61: Fecha / Date: | R61: =R4 -> 46216
B62: RUC: 20494224314
B63: Mza ñ lote.3 AH micaela Bastidas- Marcona
B64: Teléfono: 056-525092
B66: 5. Suministros a cargo de PROMCOSER
D69: Suministros a Cargo de PROMCOSER
D70: 5.1. Personal técnico calificado para la ejecución del servicio
D71: 5.2. Suministro de EPP para todo el personal del proyecto
D72: 5.3. Equipos y herramientas en cantidad y calidad suficientes para la correcta ejecución del servicio
D73: 5.4. SCTR para todo el personal.
B80: 6. Suministros a cargo del Cliente
D83: Suministros a Cargo de Cliente
D84: 6.1. Orden de Servicio para el inicio del servicio.
D85: 6.2. Áreas de intervención liberadas al 100%, según cronograma y plan de trabajo
D86: 6.3 Area para instalaciones provisionales en el proyecto. Tales como almacen temporal y/o Oficinas, no incluye contenedores ni ningún otro implemento adicional.
D87: 6.4. Apoyo en la gestión de ingreso de personal y equipos a Site (migración) gestión en el sistema 2PERSONEL.
D88: 6.5. Suministro del cable coaxial
D89: 6.6. Gestión de liberación de area (VAPE)
B94: 7.- Consideraciones
D97: Consideraciones
C98: 7.1 | D98: Las facilidades de servicios higienicos y comedor en site sera por parte del cliente, gestión administrativa in site para el ingreso al comedor, servicios higiénicos (baños), serán suministrados por el cliente.
C99: 7.2 | D99: Se considera TUBERÍA CONDUIT FLEXIBLE CON FORRO DE PVC LIQUID TIGHT 2″
C100: 7.3 | D100: Se esta considerando para la fabricación de los buzones de paso un concreto de f'c210kg/cm2
C101: 7.4 | D101: Una vez recibida la Orden de Compra (OC), se requerirá un plazo estimado de tres (03) semanas para la migración y habilitación del personal previo al inicio del servicio.
C103: 7.5 | D103: El servicio de alquiler de nuestro equipos (retroexcavadora, minicargador, vibroapisonador, volquete, camioneta, minivan) no incluye el suministro de combustible (diésel). el costo y abastecimiento referido solo aplica dentro del site.
D105: 7.5.1 | E105: El costo y abastecimiento del petróleo requerido para la operación de la unidad serán asumidos íntegramente por El cliente durante toda la vigencia del servicio, El uso de combustible fuera del site es asumido por el contratista.
C107: 7.5 | D107: Combustible (Condición Económica) En caso el cliente requiera que PROMCOSER gestione el suministro de combustible, este será considerado como un concepto reembolsable, presentado en una línea de costo independiente y sustentado en función a los ratios de consumo y horas de operación de los equipos. La valorización se realizará en función al consumo real ejecutado, debidamente sustentado y previa validación del cliente, considerando el precio vigente del proveedor autorizado en mina (PRIMAX) al momento del suministro. A este concepto se le aplicará un recargo del 10% por gastos generales y administrativos, más 10% por utilidad. Se deja expresa constancia que este será el único concepto bajo la modalidad de reembolso, siendo todos los demás costos del servicio considerados bajo la modalidad de suma alzada.
B121: Hecho por / Handled by: | F121: =+F56 -> A. Cuellar | K121: e-mail: | L121: =L56 -> ventas@promcoser.com.pe | Q121: T.Movil: | R121: =+R56 -> 940512282

Sheet CD
C2: PROYECTO : | D2: =PRESUPUESTO!E12 -> PROYECTO: MOV. TIERRAS, FAB. E INSTALACIÓN DE BANCODUCTOS
C3: CLIENTE : | D3: =PRESUPUESTO!E9 -> AESA
C5: ITEM | D5: DESCRIPCION | E5: und | F5: metrado | G5: P.U. $ | H5: Parcial $
C6: 1 | D6: TRABAJOS PRELIMINARES | H6: =+H7+H8+H9 -> 16740.41
C7: 1.1 | D7: MOVILIZACIÓN Y DESMOVILIZACION DE PERSONAL | E7: MES | F7: 1.5 | G7: 8063.61 | H7: 12095.42
C8: 1.2 | D8: MOVILIZACION Y DESMOVILIZACION DE EQUIPOS, HERRAMIENTAS Y MATERIALES | E8: VJE | F8: 4 | G8: 407.43 | H8: =G8*F8 -> 1629.72
C9: 1.3 | D9: SEGURIDAD Y SEÑALIZACION DE PROYECTO | E9: MES | F9: 1.5 | G9: 2010.18 | H9: 3015.27
C10: 2 | D10: RAMPA ZONA SUR | H10: =+H11+H20+H29+H32 -> 33717.73
C11: 2.1 | D11: BANCO DUCTO EN VÍA | H11: 3490.48
C12: 2.1.1 | D12: EXCAVACIÓN DE ZANJA CON RETROEXCAVADORA 0.6 X 1.00M | E12: M3 | F12: 11.52 | G12: 18.26 | H12: 210.36
C13: 2.1.2 | D13: PERFILADO Y NIVELACION DE TERRENO | E13: ML | F13: 24 | G13: 17.13 | H13: 411.12
C14: 2.1.3 | D14: COLOCACION DE CAMA DE ARENA E=0.20 | E14: ML | F14: 24 | G14: 16.74 | H14: 401.76
C15: 2.1.4 | D15: FABRICACIÓN DE BANCO DUCTOS 0.20 X 0.20 X 1.00M | E15: UND | F15: 24 | G15: 51.47 | H15: 1235.28
C16: 2.1.5 | D16: INSTALACIÓN DE BANCODUCTOS | E16: UND | F16: 24 | G16: 11.41 | H16: 273.84
C17: 2.1.6 | D17: SUMINISTRO DE AFIRMADO | E17: M3 | F17: 5.76 | G17: 48.24 | H17: 277.86
C18: 2.1.7 | D18: RELLENO Y COMPACTACION EN CAPAS DE 200MM | E18: M3 | F18: 11.52 | G18: 43.67 | H18: 503.08
C19: 2.1.8 | D19: ELIMINACION DE MATERIAL EXCEDENTE D= 5 KM | E19: M3 | F19: 11.52 | G19: 15.38 | H19: 177.18
C20: 2.2 | D20: BANCO DUCTO EN CAMINO | H20: 23269.83
C21: 2.2.1 | D21: EXCAVACIÓN DE ZANJA CON RETROEXCAVADORA 0.60 X 0.80M | E21: M3 | F21: 76.8 | G21: 18.26 | H21: 1402.37
C22: 2.2.2 | D22: PERFILADO Y NIVELACION DE TERRENO | E22: ML | F22: 160 | G22: 17.13 | H22: 2740.8
C23: 2.2.3 | D23: COLOCACION DE CAMA DE ARENA E=0.20 | E23: ML | F23: 160 | G23: 16.74 | H23: 2678.4
C24: 2.2.4 | D24: FABRICACIÓN DE BANCO DUCTOS 0.20 X 0.20 X 1.00M | E24: UND | F24: 160 | G24: 51.47 | H24: 8235.2
C25: 2.2.5 | D25: INSTALACIÓN DE BANCODUCTOS | E25: UND | F25: 160 | G25: 11.41 | H25: 1825.6
C26: 2.2.6 | D26: SUMINISTRO DE AFIRMADO | E26: M3 | F26: 38.4 | G26: 48.24 | H26: 1852.42
C27: 2.2.7 | D27: RELLENO Y COMPACTACION EN CAPAS DE 200MM | E27: M3 | F27: 76.8 | G27: 43.67 | H27: 3353.86
C28: 2.2.8 | D28: ELIMINACION DE MATERIAL EXCEDENTE D= 5 KM | E28: M3 | F28: 76.8 | G28: 15.38 | H28: 1181.18
C29: 2.3 | D29: CAJAS DE REGISTRO | H29: 2602.48
C30: 2.3.1 | D30: SUMINISTRO DE BUZON DE PASO 0.60 X 0.60 X 0.80M | E30: UND | F30: 8 | G30: 269.83 | H30: 2158.64
C31: 2.3.2 | D31: INSTALACIÓN DE BUZON DE PASO | E31: UND | F31: 8 | G31: 55.48 | H31: 443.84
C32: 2.4 | D32: TENDIDO DE TUBERIA FLEXIBLE | H32: 4354.94
C33: 2.4.1 | D33: SUMINISTRO TUBERÍA CONDUIT FLEXIBLE CON FORRO DE PVC LIQUID TIGHT 2″ Y ACCESORIOS | E33: GLB | F33: 1 | G33: 2658.74 | H33: 2658.74
C34: 2.4.2 | D34: INSTALACIÓN DE TUBERIA FLEXIBLE | E34: ML | F34: 165 | G34: 10.28 | H34: 1696.2
C35: 3 | D35: RAMPA ZONA NORTE | H35: =+H36+H45+H54+H57 -> 38703.02
C36: 3.1 | D36: BANCO DUCTO EN VÍA | H36: 3782.59
C37: 3.1.1 | D37: EXCAVACIÓN DE ZANJA CON RETROEXCAVADORA 0.60 X 1.00M | E37: M3 | F37: 14.4 | G37: 18.26 | H37: 262.94
C38: 3.1.2 | D38: PERFILADO Y NIVELACION DE TERRENO | E38: ML | F38: 24 | G38: 17.13 | H38: 411.12
C39: 3.1.3 | D39: COLOCACION DE CAMA DE ARENA E=0.20 | E39: ML | F39: 24 | G39: 16.74 | H39: 401.76
C40: 3.1.4 | D40: FABRICACIÓN DE BANCO DUCTOS 0.20 X 0.20 X 1.00M | E40: UND | F40: 24 | G40: 51.47 | H40: 1235.28
C41: 3.1.5 | D41: INSTALACIÓN DE BANCODUCTOS | E41: UND | F41: 24 | G41: 11.41 | H41: 273.84
C42: 3.1.6 | D42: SUMINISTRO DE AFIRMADO | E42: M3 | F42: 7.2 | G42: 48.24 | H42: 347.33
C43: 3.1.7 | D43: RELLENO Y COMPACTACION EN CAPAS DE 200MM | E43: M3 | F43: 14.4 | G43: 43.67 | H43: 628.85
C44: 3.1.8 | D44: ELIMINACION DE MATERIAL EXCEDENTE D= 5 KM | E44: M3 | F44: 14.4 | G44: 15.38 | H44: 221.47
C45: 3.2 | D45: BANCO DUCTO EN CAMINO | H45: 27923.79
C46: 3.2.1 | D46: EXCAVACIÓN DE ZANJA CON RETROEXCAVADORA 0.60 X 0.80M | E46: M3 | F46: 92.16 | G46: 18.26 | H46: 1682.84
C47: 3.2.2 | D47: PERFILADO Y NIVELACION DE TERRENO | E47: ML | F47: 192 | G47: 17.13 | H47: 3288.96
C48: 3.2.3 | D48: COLOCACION DE CAMA DE ARENA E=0.20 | E48: ML | F48: 192 | G48: 16.74 | H48: 3214.08
C49: 3.2.4 | D49: FABRICACIÓN DE BANCO DUCTOS 0.20 X 0.20 X 1.00M | E49: UND | F49: 192 | G49: 51.47 | H49: 9882.24
C50: 3.2.5 | D50: INSTALACIÓN DE BANCODUCTOS | E50: UND | F50: 192 | G50: 11.41 | H50: 2190.72
C51: 3.2.6 | D51: SUMINISTRO DE AFIRMADO | E51: M3 | F51: 46.08 | G51: 48.24 | H51: 2222.9
C52: 3.2.7 | D52: RELLENO Y COMPACTACION EN CAPAS DE 200MM | E52: M3 | F52: 92.16 | G52: 43.67 | H52: 4024.63
C53: 3.2.8 | D53: ELIMINACION DE MATERIAL EXCEDENTE D= 5 KM | E53: M3 | F53: 92.16 | G53: 15.38 | H53: 1417.42
C54: 3.3 | D54: CAJAS DE REGISTRO | H54: 2624.8
C55: 3.3.1 | D55: SUMINISTRO DE BUZON DE PASO 0.60 X 0.60 X 0.80M | E55: UND | F55: 8 | G55: 272.62 | H55: 2180.96
C56: 3.3.2 | D56: INSTALACIÓN DE BUZON DE PASO | E56: UND | F56: 8 | G56: 55.48 | H56: 443.84
C57: 3.4 | D57: TENDIDO DE TUBERIA FLEXIBLE | H57: =+H58+H59 -> 4371.84
C58: 3.4.1 | D58: SUMINISTRO TUBERÍA CONDUIT FLEXIBLE CON FORRO DE PVC LIQUID TIGHT 2″ Y ACCESORIOS | E58: GLB | F58: 1 | G58: 2624.24 | H58: 2624.24
C59: 3.4.2 | D59: INSTALACIÓN DE TUBERIA FLEXIBLE | E59: ML | F59: 170 | G59: 10.28 | H59: =G59*F59 -> 1747.6
C60: 4 | D60: TENDIDO DE CABLE COAXIAL | H60: 3167.1
C61: 4.1 | D61: TENDIDO DE CABLE COAXIAL | E61: ML | F61: 765 | G61: 4.14 | H61: 3167.1
C62: 5 | D62: MOVILIZACIÓN DE BANCODUCTOS | H62: 7277.92
C63: 5.1 | D63: MOVILIZACIÓN Y DESCARGA DE BANCO DUCTOS | E63: VJE | F63: 8 | G63: 909.74 | H63: 7277.92
C64: 6 | D64: MINICARGADOR | H64: 14508
C65: 6.1 | D65: DESCARGA / ACARREO DE BANCODUCTOS CON MINICARGADOR (INCL. OPERADOR Y VIGIA) | E65: DIA | F65: 45 | G65: 322.4 | H65: 14508
C66: 7 | D66: PARIHUELAS | H66: 414
C67: 7.1 | D67: SUMINISTRO DE PARIHUELAS PARA ALMACENAMIENTO | E67: UND | F67: 45 | G67: 9.2 | H67: 414
C68: 8 | D68: TRAZO Y REPLANTEO | H68: 9279.78
C69: 8.1 | D69: TRAZO Y REPLANTEO CON ESTACIÓN TOTAL | E69: MES | F69: 1.5 | G69: 6186.52 | H69: 9279.78
D70: Costo directo | H70: =+H68+H66+H64+H62+H60+H35+H10+H6 -> 123807.96

Sheet APU
A1: ANALISIS DE COSTOS UNITARIOS
A2: PROYECTO: MOV. TIERRAS, FAB. E INSTALACIÓN DE BANCODUCTOS - AESA
A3: CLIENTE: AESA
A4: UBICACION: MINA JUSTA - ICA - NASCA - MARCONA
A5: FECHA BASE: 2026-04-15
A6: MONEDA: DOLARES
A8: 1.1 MOVILIZACIÓN Y DESMOVILIZACION DE PERSONAL
A9: Rendimiento: 1.0000 MES/DIA | C9: Unidad: MES | E9: Costo Unitario: | F9: 8063.61
A10: Insumo | B10: Unidad | C10: Cuadrilla | D10: Cantidad | E10: PU | F10: Parcial
A11: CONDUCTOR | B11: MES | C11: 0 | D11: 3 | E11: 1187.87 | F11: 3563.61
E12: Mano de obra: | F12: 3563.61
A14: PETROLEO | B14: GAL | D14: 0 | E14: 5.1 | F14: 0
E15: Materiales: | F15: 0
A17: CAMIONETA PICK UP | B17: MES | C17: 0 | D17: 1 | E17: 1800 | F17: 1800
A18: MINIVAN 14 PASAJEROS | B18: MES | C18: 0 | D18: 1 | E18: 2700 | F18: 2700
E19: Equipo: | F19: 4500
A20: CONDUCTOR | B20: HH | C20: 1 | D20: 624 | E20: 0 | F20: 0
E21: Mano de obra: | F21: 0
A23: 1.2 MOVILIZACION Y DESMOVILIZACION DE EQUIPOS, HERRAMIENTAS Y MATERIALES
A24: Rendimiento: 2.0000 VJE/DIA | C24: Unidad: VJE | E24: Costo Unitario: | F24: =+F29+F33 -> 407.43
A25: Insumo | B25: Unidad | C25: Cuadrilla | D25: Cantidad | E25: PU | F25: Parcial
A26: CAPATAZ. | B26: HH | C26: 0.1 | D26: 0.4 | E26: 15.38 | F26: 6.15
A27: OPERADOR DE EQUIPO LIVIANO | B27: HH | C27: 1 | D27: 4 | E27: 13.46 | F27: 53.84
A28: VIGIA | B28: HH | C28: 1 | D28: 4 | E28: 11.86 | F28: 47.44
E29: Mano de obra: | F29: 107.43
A32: CAMION BARANDA | B32: HM | C32: 1 | D32: 4 | E32: 75 | F32: 300
E33: Equipo: | F33: 300
A36: 1.3 SEGURIDAD Y SEÑALIZACION DE PROYECTO
A37: Rendimiento: 1.0000 ME/DIA | C37: Unidad: ME | E37: Costo Unitario: | F37: 2010.18
A38: Insumo | B38: Unidad | C38: Cuadrilla | D38: Cantidad | E38: PU | F38: Parcial
A39: CAPATAZ | B39: MES | C39: 0 | D39: 0.1 | E39: 1484.84 | F39: 148.48
A40: OPERARIO | B40: MES | C40: 0 | D40: 0.5 | E40: 1272.72 | F40: 636.36
E41: Mano de obra: | F41: 784.84
A43: SEÑALETICA INFORMATIVA | B43: UND | D43: 15 | E43: 22.8 | F43: 342
A44: CABALLETES | B44: UND | D44: 5 | E44: 14.4 | F44: 72
A45: CONOS DE SEÑALIZACION | B45: UND | D45: 30 | E45: 10.8 | F45: 324
A46: BARRAS RETRACTILES | B46: UND | D46: 30 | E46: 8.77 | F46: 263.1
A47: BATERIA DE RESIDUOS SOLIDOS | B47: GLB | D47: 1 | E47: 65 | F47: 65
A48: ESTACION DE EMERGENCIA | B48: GLB | D48: 1 | E48: 120 | F48: 120
E49: Materiales: | F49: 1186.1
A51: HERRAMIENTAS MANUALES | B51: %MO | D51: 5 | E51: 784.84 | F51: 39.24
E52: Equipo: | F52: 39.24
A53: CAPATAZ | B53: HH | C53: 1 | D53: 20.8 | E53: 0 | F53: 0
A54: OPERARIO | B54: HH | C54: 1 | D54: 104 | E54: 0 | F54: 0
E55: Mano de obra: | F55: 0
A56: 2.1.1 EXCAVACIÓN DE ZANJA CON RETROEXCAVADORA H=1.00M
A57: Rendimiento: 30.0000 M3/DIA | C57: Unidad: M3 | E57: Costo Unitario: | F57: 18.26
A58: Insumo | B58: Unidad | C58: Cuadrilla | D58: Cantidad | E58: PU | F58: Parcial
A59: CAPATAZ. | B59: HH | C59: 0.1 | D59: 0.0267 | E59: 15.38 | F59: 0.41
A60: OPERADOR DE LINEA AMARILLA | B60: HH | C60: 1 | D60: 0.2667 | E60: 15.2 | F60: 4.05
A61: VIGIA | B61: HH | C61: 1 | D61: 0.2667 | E61: 11.86 | F61: 3.16
E62: Mano de obra: | F62: 7.62
A64: CAL DE OBRA X 10KG | B64: UND | D64: 0.02507 | E64: 2.36 | F64: 0.06
A65: RETROEXCAVADORA JOHN DEERE 310G | B65: HM | D65: 0.2667 | E65: 38.23 | F65: 10.2
E66: Materiales: | F66: 10.26
A68: HERRAMIENTAS MANUALES | B68: %MO | D68: 5 | E68: 7.62 | F68: 0.38
E69: Equipo: | F69: 0.38
A72: 2.1.2 PERFILADO Y NIVELACION DE TERRENO
A73: Rendimiento: 20.0000 ML/DIA | C73: Unidad: ML | E73: Costo Unitario: | F73: 17.13
A74: Insumo | B74: Unidad | C74: Cuadrilla | D74: Cantidad | E74: PU | F74: Parcial
A75: CAPATAZ. | B75: HH | C75: 0.1 | D75: 0.04 | E75: 15.38 | F75: 0.62
A76: OPERARIO | B76: HH | C76: 1 | D76: 0.4 | E76: 13.47 | F76: 5.39
A77: OFICIAL | B77: HH | C77: 1 | D77: 0.4 | E77: 13.37 | F77: 5.35
E78: Mano de obra: | F78: 11.36
A80: AGUA | B80: M3 | D80: 0.02 | E80: 6.2 | F80: 0.12
E81: Materiales: | F81: 0.12
A83: HERRAMIENTAS MANUALES | B83: %MO | D83: 5 | E83: 11.36 | F83: 0.57
A84: ROTOMARTILLO | B84: HM | C84: 1 | D84: 0.4 | E84: 3.5 | F84: 1.4
A85: GRUPO ELECTROGENO 11KW | B85: HM | C85: 1 | D85: 0.4 | E85: 9.2 | F85: 3.68
E86: Equipo: | F86: 5.65
A89: 2.1.3 COLOCACION DE CAMA DE ARENA E=0.20
A90: Rendimiento: 60.0000 ML/DIA | C90: Unidad: ML | E90: Costo Unitario: | F90: 16.74
A91: Insumo | B91: Unidad | C91: Cuadrilla | D91: Cantidad | E91: PU | F91: Parcial
A92: CAPATAZ. | B92: HH | C92: 0.1 | D92: 0.0133 | E92: 15.38 | F92: 0.2
A93: PEON. | B93: HH | C93: 1 | D93: 0.1333 | E93: 11.86 | F93: 1.58
A94: OFICIAL | B94: HH | C94: 1 | D94: 0.1333 | E94: 13.37 | F94: 1.78
E95: Mano de obra: | F95: 3.56
A97: ARENA FINA | B97: M3 | D97: 0.12 | E97: 25.03 | F97: 3
E98: Materiales: | F98: 3
A100: HERRAMIENTAS MANUALES | B100: %MO | D100: 5 | E100: 3.56 | F100: 0.18
A101: CAMION VOLQUETE DE 15 m3 | B101: HM | C101: 1 | D101: 0.1333 | E101: 75 | F101: 10
E102: Equipo: | F102: 10.18
A105: 2.1.4 FABRICACIÓN DE BANCO DUCTOS 0.20 X 0.20 X 1.00M
A106: Rendimiento: 1.0000 UND/DIA | C106: Unidad: UND | E106: Costo Unitario: | F106: 51.47
A107: Insumo | B107: Unidad | C107: Cuadrilla | D107: Cantidad | E107: PU | F107: Parcial
A108: TUBO SAP PVC 2"X3M ELECTRICO PAVCO | B108: UND | D108: 0.3333 | E108: 21.64 | F108: 7.21
E109: Materiales: | F109: 7.21
A111: PREPARACION Y COLOCACION DE CONCRETO F'C=210KG/CM2 | B111: M3 | D111: 0.041 | E111: 284.38 | F111: 11.66
A112: ENCOFRADO Y DESENCOFRADO | B112: M2 | D112: 0.9 | E112: 36.22 | F112: 32.6
E113: Sub Partidas: | F113: 44.26
A114: CAPATAZ | B114: HH | C114: 1 | D114: 0.077834809 | E114: 0 | F114: 0
A115: OFICIAL | B115: HH | C115: 1 | D115: 0.71676635 | E115: 0 | F115: 0
A116: OPERARIO | B116: HH | C116: 1 | D116: 0.81982792 | E116: 0 | F116: 0
A117: PEON | B117: HH | C117: 1 | D117: 0.25515426 | E117: 0 | F117: 0
E118: Mano de obra: | F118: 0
A120: 2.1.5 INSTALACIÓN DE BANCODUCTOS
A121: Rendimiento: 40.0000 UND/DIA | C121: Unidad: UND | E121: Costo Unitario: | F121: 11.41
A122: Insumo | B122: Unidad | C122: Cuadrilla | D122: Cantidad | E122: PU | F122: Parcial
A123: CAPATAZ. | B123: HH | C123: 0.1 | D123: 0.02 | E123: 15.38 | F123: 0.31
A124: OPERARIO | B124: HH | C124: 1 | D124: 0.2 | E124: 13.47 | F124: 2.69
...

Sheet PS..
C2: PROYECTO : | D2: =+PRESUPUESTO!C26 -> PROYECTO: MOV. TIERRAS, FAB. E INSTALACIÓN DE BANCODUCTOS
C3: CLIENTE : | D3: MARCOBRE - MINA JUSTA
C4: EJECUCION : | D4: 30 | E4: Dias
F5: =8175/30 -> 272.5
C6: ITEM | D6: DESCRIPCION | E6: UND | F6: METRADO | G6: P.U.$ | H6: Parcial $
C7: 01 | D7: OBRAS PRELIMINARES | H7: =SUM(H8:H12) -> #REF!
C8: 01.01 | D8: MOVILIZACION Y DESMOVILIZACION DE PERSONAL | E8: mes | F8: 1 | G8: 8175 | H8: =G8*F8 -> 8175
C9: 01.02 | D9: MOVILIZACION Y DESMOVILIZACION DE EQUIPOS, HERRAMIENTAS Y MATERIALES | E9: vje | F9: 1 | G9: 479.06 | H9: =G9*F9 -> 479.06
C10: 01.03 | D10: SEGURIDAD Y SEÑALIZACION DE OBRA | E10: glb | F10: 1 | G10: 2615.85 | H10: =G10*F10 -> 2615.85
C11: 01.04 | D11: MOVILIZACIÓN Y DESMOVILIZACIÓN DE MANLIFT | E11: vje | F11: 2 | G11: =APU!#REF! -> #REF! | H11: =G11*F11 -> #REF!
C12: 01.05 | D12: ALQUILER DE MANLITF (Inc. Operador) | E12: día | F12: 30 | G12: =APU!#REF! -> #REF! | H12: =G12*F12 -> #REF!
C13: 02 | D13: INSTALACION DE PUERTA DE INGRESO | H13: =SUM(H14:H17) -> 947.01
C14: 02.01 | D14: ARMADO Y DESARMADO DE TORRE DE ANDAMIOS x 2 CUERPOS HERMETIZADO | E14: día | F14: 2 | G14: 97.18 | H14: =+G14*F14 -> 194.36
C15: 02.02 | D15: RETIRO Y ELIMINACION DE ESTRUCTURA DAÑADA | E15: kg | F15: 20 | G15: 0.69 | H15: =+G15*F15 -> 13.8
C16: 02.03 | D16: FABRICACION DE PUERTA METALICA 1.6x2.1 mt (Inc. Chapa y accesorios) | E16: und | F16: 1 | G16: 563.05 | H16: =+G16*F16 -> 563.05
C17: 02.04 | D17: INSTALACION DE PUERTA METALICA Y ACCESORIOS | E17: kg | F17: 60 | G17: 2.93 | H17: =+G17*F17 -> 175.8
C18: 03 | D18: CIERRE DE ACCESOS | H18: =SUM(H19:H23) -> 1606.2
C19: 03.01 | D19: ARMADO Y DESARMADO DE TORRE DE ANDAMIOS x 2 CUERPOS | E19: día | F19: 2 | G19: 176.6 | H19: =G19*F19 -> 353.2
C20: 03.02 | D20: FABRICACION DE ESTRUCTURA LIVIANA INOXIDABLE | E20: kg | F20: 40 | G20: 12.68 | H20: =G20*F20 -> 507.2
C21: 03.03 | D21: MONTAJE DE ESTRUCTURA LIVIANA | E21: kg | F21: 40 | G21: 2.3 | H21: =G21*F21 -> 92
C22: 03.04 | D22: SUMINISTRO DE LONA PLAST DG1330-BO | E22: m2 | F22: 20 | G22: MCB
C23: 03.05 | D23: INSTALACION DE LONAPLAST DG1330 - BO | E23: m2 | F23: 20 | G23: 32.69 | H23: =G23*F23 -> 653.8
C24: 04 | D24: MANTENIMIENTO ESTRUCTURAL - PUERTAS CORREDIZAS | H24: =+SUM(H25:H34) -> 10027.93
C25: 04.01 | D25: ARMADO Y DESARMADO DE TORRE DE ANDAMIOS x 6 CUERPOS | E25: día | F25: 8 | G25: 218.59 | H25: =+G25*F25 -> 1748.72
C26: 04.02 | D26: RETIRO Y REINSTALACION DE LONA PLAST DG1330-BO | E26: m2 | F26: 100 | G26: 4.55 | H26: =+G26*F26 -> 455
C27: 04.03 | D27: LIMPIEZA MANUAL CON EQUIPOS | E27: m2 | F27: 60 | G27: 17.49 | H27: =+G27*F27 -> 1049.4
C28: 04.04 | D28: APLICACION DE PINTURA BASE ESMALTE EPOXICO JET 70 MP | E28: m2 | F28: 60 | G28: 24.96 | H28: =+G28*F28 -> 1497.6
C29: 04.05 | D29: APLICACION DE PINTURA ACABADO POLIURETANO JETHANE 650 HS | E29: m2 | F29: 60 | G29: 17.73 | H29: =+G29*F29 -> 1063.8
C30: 04.06 | D30: REEMPLAZO DE CABLE ACERADO PARA PUERTA CORREDIZA | E30: m | F30: 100 | G30: 6.97 | H30: =+G30*F30 -> 697
C31: 04.07 | D31: REEMPLAZO DE RIEL GUIA PARA PUERTA CORREDIZA | E31: m | F31: 50 | G31: 43.78 | H31: =+G31*F31 -> 2189
C32: 04.08 | D32: REEMPLAZO DE POLEAS PARA PUERTAS CORREDIZAS | E32: und | F32: 32 | G32: 26.02 | H32: =+G32*F32 -> 832.64
C33: 04.09 | D33: REEMPLAZO DE WINCHES MANUALES 800 LB | E33: und | F33: 4 | G33: 89.88 | H33: =+G33*F33 -> 359.52
C34: 04.10 | D34: REPARACION DE MANIVELAS Y PESTILLOS MENORES | E34: und | F34: 5 | G34: 27.05 | H34: =+G34*F34 -> 135.25
C35: 05 | D35: HERMETIZACION DE TECHOS | H35: =SUM(H36:H37) -> 1961.4
C36: 05.01 | D36: SUMINISTRO DE LONA PLAST DG1330-BO | E36: m2 | F36: 60 | G36: MCB
C37: 05.02 | D37: INSTALACION DE LONAPLAST DG1330 - BO | E37: m2 | F37: 60 | G37: 32.69 | H37: =+G37*F37 -> 1961.4
C38: 06 | D38: LIMPIEZA DE COBERTORES TRANSLUCIDAS - TECHO ALMACEN CENTRAL | H38: =SUM(H39:H40) -> #REF!
C39: 06.01 | D39: LIMPIEZA DE COBERTORES DE TECHI | E39: Und | F39: 12 | G39: =APU!#REF! -> #REF! | H39: =+G39*F39 -> #REF!
C40: 06.02 | D40: LIMPIEZA DE ACCESOS POSTLAVADO | E40: ml | F40: 110 | G40: =APU!#REF! -> #REF! | H40: =+G40*F40 -> #REF!
C41: 07 | D41: INSTALACION DE EXTRACTORES EOLICOS - TECHO ALMACEN CENTRAL | H41: =SUM(H42:H43) -> #REF!
C42: 07.01 | D42: RETIRO Y ELIMINACIÓN DE EXTRACTORES EOLICOS EXISTENTES | E42: Und | F42: 10 | G42: =APU!#REF! -> #REF! | H42: =+G42*F42 -> #REF!
C43: 07.02 | D43: SUMINISTRO E INSTALACIÓN DE EXTRACTORES EOLICOS "INDUVENT EO80" | E43: Und | F43: 12 | G43: =APU!#REF! -> #REF! | H43: =+G43*F43 -> #REF!
C44: 08 | D44: LIMPIEZA DE FILTROS DE VENTANAS | H44: =SUM(H45:H47) -> #REF!
C45: 08.01 | D45: DESINSTALACIÓN DE FILTROS DE VENTANA (4 UND/VENTANA) | E45: Und | F45: 40 | G45: =APU!#REF! -> #REF! | H45: =G45*F45 -> #REF!
C46: 08.02 | D46: SOPLETEO DE FILTROS | E46: Und | F46: 40 | G46: =APU!#REF! -> #REF! | H46: =G46*F46 -> #REF!
C47: 8.03 | D47: REINSTALACIÓN DE VENTANAS | E47: Und | F47: 40 | G47: =APU!#REF! -> #REF! | H47: =G47*F47 -> #REF!
C48: 06 | D48: SUPERVISIÓN DE TRABAJOS | H48: =H49 -> #REF!
C49: 06.01 | D49: SUPERVISION DE SERVICIOS MENORES | E49: mes | F49: 1 | G49: =APU!#REF! -> #REF! | H49: =G49*F49 -> #REF!
C50: Costo Directo | G50: =+H48+H35+H24+H38+H41+H44+H18+H13+H7 -> #REF!

Sheet GG
B2: ANALISIS DE GASTOS GENERALES (PROYECTOS MENORES)
B4: PROYECTO: | C4: =+'PS..'!D2 -> PROYECTO: MOV. TIERRAS, FAB. E INSTALACIÓN DE BANCODUCTOS
B5: OBRA: | C5: =+C4 -> PROYECTO: MOV. TIERRAS, FAB. E INSTALACIÓN DE BANCODUCTOS
B6: CONTRATISTA: | C6: PROMCOSER SRL
B7: FECHA: | C7: 46133
B8: PLAZO PROYECTO (MESES): | D8: 1.5
B11: ANALISIS DE GASTOS GENERALES
B12: Item | C12: DESCRIPCION | D12: UND | E12: CAN. | F12: MES | H12: PARCIAL | I12: TOTAL
G13: SALARIO BAS. MES | H13: COSTO MENSUAL incluye BB.SS.
G15: $. | H15: $. | I15: $.
B16: 1 | C16: ÁREA TÉCNICA
C17: Residente de Obra | D17: mes | E17: 1 | F17: 0 | G17: 2300 | H17: =+G17*1.45 -> 3335 | I17: =E17*F17*H17 -> 0
C18: Ingeniero de Calidad | D18: mes | E18: 1.5 | F18: 1 | G18: =6031.4/3.4 -> 1773.9412 | H18: =+G18*1.45 -> 2572.2147 | I18: =E18*F18*H18 -> 3858.3221
C19: Ingeniero de oficina tecnica | D19: mes | E19: 1 | F19: 0.5 | G19: =6000/3.3 -> 1818.1818 | H19: =+G19*1.45 -> 2636.3636 | I19: =E19*F19*H19 -> 1318.1818
C20: Relevo de supervision | D20: mes | E20: 1.5 | F20: 1 | G20: =5125.11/3.45 -> 1485.5391 | H20: =+G20*1.45 -> 2154.0317 | I20: =E20*F20*H20 -> 3231.0476
C21: Ingeniero de seguridad | D21: mes | E21: 1.5 | F21: 1 | G21: =4714.51/3.4 -> 1386.6206 | H21: =+G21*1.45 -> 2010.5999 | I21: =E21*F21*H21 -> 3015.8998
E23: =SUM(E17:E22) -> 6.5 | H23: 1 | I23: =SUM(I17:I22) -> 11423.451
B24: 2 | C24: EMPLEADO
C25: CONDUCTOR | D25: mes | E25: 1 | F25: 0.5 | G25: 757.58 | H25: =+G25*1.45 -> 1098.491 | I25: =E25*F25*H25 -> 549.2455
C26: ALMACEN | D26: mes | E26: 1 | F26: 0.5 | G26: 757.58 | H26: =+G26*1.45 -> 1098.491 | I26: =E26*F26*H26 -> 549.2455
E29: =SUM(E25:E28) -> 2 | H29: 2 | I29: =SUM(I25:I28) -> 1098.491
B30: 3 | C30: VEHICULOS: CAMIONETAS, BUSES.
C31: Vehiculos | G31: COSTO $.
C32: Camioneta incluye combustible | D32: mes | E32: 1 | F32: 0.5 | G32: =60*30 -> 1800 | I32: =E32*G32*F32 -> 900
C33: Bus Movilidad a Obra incluye combustible | D33: mes | E33: 1 | F33: 0.5 | G33: =120*5.1 -> 612 | I33: =E33*G33*F33 -> 306
H35: 3 | I35: =SUM(I31:I34) -> 1206
B36: 4 | C36: SEGURIDAD
C37: Implementos seguridad (solo staff de ingenieros, EPP de obreros debe ser considerada en el costo de horas hombre dentro del costo directo) | D37: Pers | E37: 2 | G37: =350/3 -> 116.66667 | I37: =E37*G37 -> 233.33333
C38: Exámenes Médicos Ocupacional (Staff y obreros) | D38: Pers | E38: 2 | G38: =284/3.4/3 -> 27.843137 | I38: =E38*G38 -> 55.686275
C39: Pruebas y ensayos | D39: Glb | E39: 1 | G39: 400 | I39: =E39*G39 -> 400
C40: Cursos y Capacitaciones | D40: Pers | E40: 2 | G40: =560/3.4/3 -> 54.901961 | I40: =E40*G40 -> 109.80392
C41: Cursos Basicos portuarios: PBIP Basico Seguridad portuaria Mercancias peligrosas | D41: Pers | G41: =45*3 -> 135 | I41: =E41*G41 -> 0
C42: Gestion Portuaria: Gestion de seguridad portuaria Gestion de mercancias peligrosas | D42: Pers | G42: 176 | I42: =E42*G42 -> 0
H45: 4 | I45: =SUM(I37:I44) -> 798.82353
B46: 5 | C46: EQUIPOS: OFICINA, COMPUTO, COMUNICACIONES. | E46: Cant | F46: Incidencia | G46: COSTO/mes
C47: Equipos
C48: computadoras completas | E48: 2 | F48: 0.3 | G48: 484.84848 | I48: =G48*F48*E48 -> 290.90909
C49: telefono celular | E49: 2 | F49: 1 | G49: 27.272727 | I49: =G49*F49*E49 -> 54.545455
C51: Equipos de Campamentos
C52: alquiler de vivienda para staff | E52: 2 | F52: 1 | G52: 151.51515 | I52: =G52*F52*E52 -> 303.0303
C53: alimentacion staff | E53: 2 | F53: 1 | G53: 333.33333 | I53: =G53*F53*E53 -> 666.66667
C54: agua para personal | E54: 1 | F54: 20 | G54: 6.6969697 | I54: =G54*F54*E54 -> 133.93939
H56: 5 | I56: =SUM(I48:I54) -> 1449.0909
B57: 6 | C57: GASTOS DE OFICINA CENTRAL | H57: COSTO X MES
C58: Logistica | D58: mes | E58: 1 | F58: 0.3 | H58: =2000*1.45/3.3 -> 878.78788 | I58: =+H58*F58*E58 -> 263.63636
C59: Contabilidad y recursos humanos | D59: mes | E59: 1 | F59: 0.3 | H59: =2000*1.45/3.3 -> 878.78788 | I59: =+H59*F59*E59 -> 263.63636
C60: Gerencia de Operaciones (%) | D60: mes | E60: 1 | F60: 0.3 | H60: =6200*1.45/3.3 -> 2724.2424 | I60: =+H60*F60*E60 -> 817.27273
C61: Utiles de Oficina Gerencia | D61: mes | E61: 1 | F61: 0.3 | H61: =363/3.3 -> 110 | I61: =+H61*F61*E61 -> 33
C62: Oficina y servicios | D62: mes | E62: 1 | F62: 0.3 | H62: =345/3.3 -> 104.54545 | I62: =+H62*F62*E62 -> 31.363636
C63: Equipos de computo | D63: mes | E63: 1 | F63: 0.3 | H63: 254.14 | I63: =+H63*F63*E63 -> 76.242
H65: 6 | I65: =SUM(I58:I63) -> 1485.1511
B66: 7 | C66: SEGUROS Y FIANZAS | E66: Cant | G66: COSTO/mes
C67: Costo de carta fianza fiel cumplimiento del 15% del Contrato | E67: 0 | F67: 0.0015 | I67: =+E67*G67*F67 -> 0
C68: Costo de carta fianza de adelanto | E68: 0 | F68: 0.002 | I68: =+E68*G68*F68 -> 0
C69: Seguro Vehicular | E69: 1 | G69: =7000/12/3.4 -> 171.56863 | I69: =+E69*G69 -> 171.56863
C70: Gastos Financieros | E70: 1 | G70: 550 | I70: =+E70*G70 -> 550
H71: 7 | I71: =SUM(I67:I70) -> 721.56863
G73: GG MENSUAL | I73: =(+I56+I45+I35+I29+I23+I71+I65) -> 18182.576
G74: MESES | H74: 1.5 | I74: =+I73*H74 -> 27273.865

Sheet COMBUSTIBLE
A2: ITEM | B2: DESCRIPCION DEL EQUIPO | C2: CANTIDAD DE EQUIPOS | D2: CONSUMO (Gln/ HE) | E2: HORA MINIMA | F2: UND | G2: METRADO | H2: CONSUMO PARCIAL
A3: 01 | B3: Retroexcavadora | C3: 1 | D3: 2 | E3: 6 | F3: Dias | G3: 45 | H3: =E3*D3*C3*G3 -> 540
A4: 02 | B4: Camioneta | C4: 1 | D4: 1 | E4: 120 | F4: Mes | G4: 1.5 | H4: =E4*D4*C4*G4 -> 180
A5: 03 | B5: Minivan | C5: 1 | D5: 1 | E5: 120 | F5: Mes | G5: 1.5 | H5: =E5*D5*C5*G5 -> 180
A6: 04 | B6: Volquete 20m3 | C6: 1 | D6: 5 | E6: 4 | F6: vje | G6: 26 | H6: =E6*D6*C6*G6 -> 520
A7: 05 | B7: Camión | C7: 1 | D7: 4 | E7: 4 | F7: vje | G7: 12 | H7: =E7*D7*C7*G7 -> 192
A8: 06 | B8: Vibroapisonador | C8: 1 | D8: 0.25 | E8: 6 | F8: Dias | G8: 30 | H8: =E8*D8*C8*G8 -> 45
A9: 07 | B9: Minicargador | C9: 1 | D9: 1.5 | E9: 6 | F9: Dias | G9: 45 | H9: =E9*D9*C9*G9 -> 405
F10: TOTAL CONSUMO / GALONES | H10: =SUM(H3:H9) -> 2062
F12: Costo por combustile (reembolsable) | H12: =H10*3.87 -> 7979.94
F13: GG | G13: 0.1 | H13: =H12*G13 -> 797.994
F14: UTILIDAD | G14: 0.1 | H14: =G14*H12 -> 797.994
F15: TOTAL SIN IGV | H15: =+H14+H13+H12 -> 9575.928

Sheet METRADO
B2: RAMPA SUR
B3: N° | C3: DESCRIPCIÓN | D3: Unidad | E3: Metrado
B4: 1 | C4: Bancoducto en vía
B5: 1.1 | C5: Excavación de zanja 0.60 x 1.00m | D5: m3 | E5: =0.6*0.8*24 -> 11.52
B6: 1.2 | C6: Bancoducto de 1.00m | D6: und | E6: 24
B7: 1.3 | C7: Tubería de PVC SAP 2" | D7: m | E7: 24
B8: 1.5 | C8: Suministro de cable coaxial - AESA | D8: m | E8: 30
B10: 2 | C10: Bancoducto en camino
B11: 2.1 | C11: Excavación de zanja 0.60 x 0.80m | D11: m3 | E11: =0.6*0.8*160 -> 76.8
B12: 2.2 | C12: Bancoducto de 1.00 | D12: und | E12: 160
B13: 2.3 | C13: Tubería de PVC SAP 2" | D13: m | E13: 160
B14: 2.5 | C14: Suministro de cable coaxial - AESA | D14: m | E14: 166
B16: 3 | C16: Cajas de registro | F16: =E8+E14+E20+E30+E36+E42 -> 765
B17: 3.1 | C17: Buzón de paso 0.8 x 0.8 x 0.8 | D17: und | E17: 8
B19: 4 | C19: Cable coaxial x tub flexible
B20: 4.1 | C20: Suministro de cable coaxial - AESA | D20: m | E20: 165
B21: 4.2 | C21: Tubería metalica 2" | D21: m | E21: 165
B22: 4.3 | C22: Alcayata | D22: und | E22: 30
B24: RAMPA NORTE
B25: N° | C25: DESCRIPCIÓN | D25: Unidad | E25: Metrado
B26: 1 | C26: Bancoducto en vía
B27: 1.1 | C27: Excavación de zanja de 0.60 x 1.00m | D27: m3 | E27: =0.6*1*24 -> 14.4
B28: 1.2 | C28: Bancoducto | D28: und | E28: 24
B29: 1.3 | C29: Tubería de PVC SAP 2" | D29: m | E29: 24
B30: 1.5 | C30: Suministro de cable coaxial - AESA | D30: m | E30: 30
B32: 2 | C32: Bancoducto en camino
B33: 2.1 | C33: Excavación de zanja de 0.60 x 0.80 m | D33: m3 | E33: =0.6*0.8*E35 -> 92.16
B34: 2.2 | C34: Bancoducto | D34: und | E34: 192
B35: 2.3 | C35: Tubería de PVC SAP 2" | D35: m | E35: 192
B36: 2.5 | C36: Suministro de cable coaxial - AESA | D36: m | E36: 198
B38: 3 | C38: Cajas de registro
B39: 3.1 | C39: Buzón de paso 0.60 x 0.60 x 0.8 m3 | D39: und | E39: 8
B41: 4 | C41: Cable coaxial x tub flexible
B42: 4.1 | C42: Suministro de cable coaxial - AESA | D42: m | E42: 176
B43: 4.2 | C43: Tubería metalica 2" | D43: m | E43: 170
B44: 4.3 | C44: Alcayata | D44: und | E44: 35

Sheet Ajuste HH MOD
A1: AJUSTE DE HH DE MANO DE OBRA DIRECTA (MOD) -- PS-065 Bancoductos
A2: Generado: 2026-09-15. Revisado con Victor a partir de 3 fuentes: hoja APU (visible), Listado de Insumos - AESA.xlsx, y la regla MES->HH (factor 208 HH/mes) definida el 2026-09-06.
A3: Objetivo: la suma de HH por partida y la suma de HH por cargo deben coincidir en el TOTAL REAL: 5,312.08 HH.
A4: IMPORTANTE: las filas marcadas ESTIMADO son un prorrateo por peso en dolares (Sub Partidas de concreto+encofrado), no vienen desglosadas por partida en ningun archivo fuente -- si AESA/PROMCOSER entrega el analisis real de esas sub-partidas, estos numeros deben corregirse.
A6: TABLA 1 -- HH por PARTIDA
A7: WBS | B7: Descripcion | C7: Metrado | D7: HH visible en APU | E7: HH ajuste | F7: Tipo de ajuste | G7: HH TOTAL partida
A8: 1.1 | B8: MOVILIZACIÓN Y DESMOVILIZACION DE PERSONAL | C8: 1.5 | D8: 0 | E8: 936 | F8: EXACTO (MES->HH, factor 208, CONDUCTOR) | G8: 936
A9: 1.2 | B9: MOVILIZACION Y DESMOVILIZACION DE EQUIPOS, HERRAMIENTAS Y MATERIALES | C9: 4 | D9: 33.6 | E9: 0 | G9: 33.6
A10: 1.3 | B10: SEGURIDAD Y SEÑALIZACION DE PROYECTO | C10: 1.5 | D10: 0 | E10: 187.2 | F10: EXACTO (MES->HH, factor 208, CAPATAZ+OPERARIO) | G10: 187.2
A11: 2.1.1 | B11: EXCAVACIÓN DE ZANJA CON RETROEXCAVADORA 0.6 X 1.00M | C11: 11.52 | D11: 6.45 | E11: 0 | G11: 6.45
A12: 2.1.2 | B12: PERFILADO Y NIVELACION DE TERRENO | C12: 24 | D12: 20.16 | E12: 0 | G12: 20.16
A13: 2.1.3 | B13: COLOCACION DE CAMA DE ARENA E=0.20 | C13: 24 | D13: 6.72 | E13: 0 | G13: 6.72
A14: 2.1.4 | B14: FABRICACIÓN DE BANCO DUCTOS 0.20 X 0.20 X 1.00M | C14: 24 | D14: 0 | E14: 44.87 | F14: ESTIMADO (prorrateo Sub Partidas concreto+encofrado) | G14: 44.87
A15: 2.1.5 | B15: INSTALACIÓN DE BANCODUCTOS | C15: 24 | D15: 14.88 | E15: 0 | G15: 14.88
A16: 2.1.6 | B16: SUMINISTRO DE AFIRMADO | C16: 5.76 | D16: 1.15 | E16: 0 | G16: 1.15
A17: 2.1.7 | B17: RELLENO Y COMPACTACION EN CAPAS DE 200MM | C17: 11.52 | D17: 31.49 | E17: 0 | G17: 31.49
A18: 2.1.8 | B18: ELIMINACION DE MATERIAL EXCEDENTE D= 5 KM | C18: 11.52 | D18: 3.46 | E18: 0 | G18: 3.46
A19: 2.2.1 | B19: EXCAVACIÓN DE ZANJA CON RETROEXCAVADORA 0.60 X 0.80M | C19: 76.8 | D19: 43.02 | E19: 0 | G19: 43.02
A20: 2.2.2 | B20: PERFILADO Y NIVELACION DE TERRENO | C20: 160 | D20: 134.4 | E20: 0 | G20: 134.4
A21: 2.2.3 | B21: COLOCACION DE CAMA DE ARENA E=0.20 | C21: 160 | D21: 44.78 | E21: 0 | G21: 44.78
A22: 2.2.4 | B22: FABRICACIÓN DE BANCO DUCTOS 0.20 X 0.20 X 1.00M | C22: 160 | D22: 0 | E22: 299.14 | F22: ESTIMADO (prorrateo Sub Partidas concreto+encofrado) | G22: 299.14
A23: 2.2.5 | B23: INSTALACIÓN DE BANCODUCTOS | C23: 160 | D23: 99.2 | E23: 0 | G23: 99.2
A24: 2.2.6 | B24: SUMINISTRO DE AFIRMADO | C24: 38.4 | D24: 7.68 | E24: 0 | G24: 7.68
A25: 2.2.7 | B25: RELLENO Y COMPACTACION EN CAPAS DE 200MM | C25: 76.8 | D25: 209.93 | E25: 0 | G25: 209.93
A26: 2.2.8 | B26: ELIMINACION DE MATERIAL EXCEDENTE D= 5 KM | C26: 76.8 | D26: 23.04 | E26: 0 | G26: 23.04
A27: 2.3.1 | B27: SUMINISTRO DE BUZON DE PASO 0.60 X 0.60 X 0.80M | C27: 8 | D27: 0 | E27: 72.97 | F27: ESTIMADO (prorrateo Sub Partidas concreto+encofrado, sin acero) | G27: 72.97
A28: 2.3.2 | B28: INSTALACIÓN DE BUZON DE PASO | C28: 8 | D28: 25.6 | E28: 0 | G28: 25.6
A29: 2.4.1 | B29: SUMINISTRO TUBERÍA CONDUIT FLEXIBLE CON FORRO DE PVC LIQUID TIGHT 2″ Y ACCESORIOS | C29: 1 | D29: 8 | E29: 0 | G29: 8
A30: 2.4.2 | B30: INSTALACIÓN DE TUBERIA FLEXIBLE | C30: 165 | D30: 110.88 | E30: 0 | G30: 110.88
A31: 3.1.1 | B31: EXCAVACIÓN DE ZANJA CON RETROEXCAVADORA 0.60 X 1.00M | C31: 14.4 | D31: 8.07 | E31: 0 | G31: 8.07
A32: 3.1.2 | B32: PERFILADO Y NIVELACION DE TERRENO | C32: 24 | D32: 20.16 | E32: 0 | G32: 20.16
A33: 3.1.3 | B33: COLOCACION DE CAMA DE ARENA E=0.20 | C33: 24 | D33: 6.72 | E33: 0 | G33: 6.72
A34: 3.1.4 | B34: FABRICACIÓN DE BANCO DUCTOS 0.20 X 0.20 X 1.00M | C34: 24 | D34: 0 | E34: 44.87 | F34: ESTIMADO (prorrateo Sub Partidas concreto+encofrado) | G34: 44.87
A35: 3.1.5 | B35: INSTALACIÓN DE BANCODUCTOS | C35: 24 | D35: 14.88 | E35: 0 | G35: 14.88
A36: 3.1.6 | B36: SUMINISTRO DE AFIRMADO | C36: 7.2 | D36: 1.44 | E36: 0 | G36: 1.44
A37: 3.1.7 | B37: RELLENO Y COMPACTACION EN CAPAS DE 200MM | C37: 14.4 | D37: 39.36 | E37: 0 | G37: 39.36
A38: 3.1.8 | B38: ELIMINACION DE MATERIAL EXCEDENTE D= 5 KM | C38: 14.4 | D38: 4.32 | E38: 0 | G38: 4.32
A39: 3.2.1 | B39: EXCAVACIÓN DE ZANJA CON RETROEXCAVADORA 0.60 X 0.80M | C39: 92.16 | D39: 51.62 | E39: 0 | G39: 51.62
A40: 3.2.2 | B40: PERFILADO Y NIVELACION DE TERRENO | C40: 192 | D40: 161.28 | E40: 0 | G40: 161.28
A41: 3.2.3 | B41: COLOCACION DE CAMA DE ARENA E=0.20 | C41: 192 | D41: 53.74 | E41: 0 | G41: 53.74
A42: 3.2.4 | B42: FABRICACIÓN DE BANCO DUCTOS 0.20 X 0.20 X 1.00M | C42: 192 | D42: 0 | E42: 358.96 | F42: ESTIMADO (prorrateo Sub Partidas concreto+encofrado) | G42: 358.96
A43: 3.2.5 | B43: INSTALACIÓN DE BANCODUCTOS | C43: 192 | D43: 119.04 | E43: 0 | G43: 119.04
A44: 3.2.6 | B44: SUMINISTRO DE AFIRMADO | C44: 46.08 | D44: 9.22 | E44: 0 | G44: 9.22
A45: 3.2.7 | B45: RELLENO Y COMPACTACION EN CAPAS DE 200MM | C45: 92.16 | D45: 251.91 | E45: 0 | G45: 251.91
A46: 3.2.8 | B46: ELIMINACION DE MATERIAL EXCEDENTE D= 5 KM | C46: 92.16 | D46: 27.65 | E46: 0 | G46: 27.65
A47: 3.3.1 | B47: SUMINISTRO DE BUZON DE PASO 0.60 X 0.60 X 0.80M | C47: 8 | D47: 1.6 | E47: 72.97 | F47: ESTIMADO (prorrateo Sub Partidas concreto+encofrado, sin acero) | G47: 74.57
A48: 3.3.2 | B48: INSTALACIÓN DE BUZON DE PASO | C48: 8 | D48: 25.6 | E48: 0 | G48: 25.6
A49: 3.4.1 | B49: SUMINISTRO TUBERÍA CONDUIT FLEXIBLE CON FORRO DE PVC LIQUID TIGHT 2″ Y ACCESORIOS | C49: 1 | D49: 8 | E49: 0 | G49: 8
A50: 3.4.2 | B50: INSTALACIÓN DE TUBERIA FLEXIBLE | C50: 170 | D50: 114.24 | E50: 0 | G50: 114.24
A51: 4.1 | B51: TENDIDO DE CABLE COAXIAL | C51: 765 | D51: 160.65 | E51: 0 | G51: 160.65
A52: 5.1 | B52: MOVILIZACIÓN Y DESCARGA DE BANCO DUCTOS | C52: 8 | D52: 198.4 | E52: 0 | G52: 198.4
A53: 6.1 | B53: DESCARGA / ACARREO DE BANCODUCTOS CON MINICARGADOR (INCL. OPERADOR Y VIGIA) | C53: 45 | D53: 568.42 | E53: 0 | G53: 568.42
A54: 7.1 | B54: SUMINISTRO DE PARIHUELAS PARA ALMACENAMIENTO | C54: 45 | D54: 0.36 | E54: 0 | G54: 0.36
A55: 8.1 | B55: TRAZO Y REPLANTEO CON ESTACIÓN TOTAL | C55: 1.5 | D55: 0 | E55: 624 | F55: EXACTO (MES->HH, factor 208, TOPOGRAFO+AYUDANTE) | G55: 624
B56: TOTAL | D56: =SUM(D8:D55) -> 2671.12 | E56: =SUM(E8:E55) -> 2640.98 | G56: =SUM(G8:G55) -> 5312.1
A59: TABLA 2 -- HH por CARGO
A60: Cargo | B60: HH visible en APU (nativo) | C60: HH Sub Partidas (estimado) | D60: HH MES->HH (exacto) | E60: HH TOTAL cargo
A61: CAPATAZ | B61: 104.16 | C61: 37.21 | D61: 31.2 | E61: 172.57
A62: OPERADOR DE EQUIPO LIVIANO | B62: 99.49 | C62: 0 | D62: 0 | E62: 99.49
A63: VIGIA | B63: 422.14 | C63: 0 | D63: 0 | E63: 422.14
A64: OPERADOR DE LINEA AMARILLA | B64: 342.14 | C64: 0 | D64: 0 | E64: 342.14
A65: OFICIAL (CIVIL) | B65: 309.32 | C65: 342.66 | D65: 0 | E65: 651.98
A66: OPERARIO (CIVIL) | B66: 401.93 | C66: 391.93 | D66: 156 | E66: 949.86
A67: PEON | B67: 587.08 | C67: 121.98 | D67: 0 | E67: 709.06
A68: LOGISTICA | B68: 37.45 | C68: 0 | D68: 0 | E68: 37.45
A69: OPERARIO ELECTRICISTA | B69: 183.7 | C69: 0 | D69: 0 | E69: 183.7
A70: OFICIAL ELECTRICISTA | B70: 183.7 | C70: 0 | D70: 0 | E70: 183.7
A71: CONDUCTOR | B71: 0 | C71: 0 | D71: 936 | E71: 936
A72: TOPOGRAFO | B72: 0 | C72: 0 | D72: 312 | E72: 312
A73: AYUDANTE TOPOGRAFO | B73: 0 | C73: 0 | D73: 312 | E73: 312
A74: TOTAL | B74: =SUM(B61:B73) -> 2671.11 | C74: =SUM(C61:C73) -> 893.78 | D74: =SUM(D61:D73) -> 1747.2 | E74: =SUM(E61:E73) -> 5312.09
